Workbook

Sheet Executive Summary
A1: NAMA KNOWLEDGE - 10-YEAR FINANCIAL MODEL
A2: Saudi Clinical Intelligence Group (Theeb Group)
A4: KEY METRICS SUMMARY
A5: Metric | B5: Value
A6: Total Investment Required | B6: $1,000,000
A7: Year 1 Revenue | B7: $1,500,000
A8: Year 5 Revenue | B8: $28,000,000
A9: Year 10 Revenue | B9: $69,100,000
A10: Year 1 EBITDA | B10: $180,000
A11: Year 5 EBITDA | B11: $12,880,000
A12: Year 10 EBITDA | B12: $33,168,000
A13: Year 1 EBITDA Margin | B13: 12.0%
A14: Year 5 EBITDA Margin | B14: 46.0%
A15: Year 10 EBITDA Margin | B15: 48.0%
A16: Gross Margin | B16: 72.0%
... A21: Y5 MOIC (Optimistic) | B21: 128.8x

Sheet Revenue Model
A1: REVENUE MODEL - 10 YEAR PROJECTIONS (2027-2036)
A3: Total Revenue ($000s) | B3: Y1 | C3: Y2 | D3: Y3 | E3: Y4 | F3: Y5 | G3: Y6 | H3: Y7 | I3: Y8 | J3: Y9 | K3: Y10
A4: LMS (30%) | B4: 450 | C4: 900 | D4: 1350 | E4: 1800 | F4: 2250 | G4: 2700 | H4: 3150 | I4: 3600 | J4: 4050 | K4: 4500
A5: CME (15%) | B5: 225 | C5: 450 | D5: 675 | E5: 900 | F5: 1125 | G5: 1350 | H5: 1575 | I5: 1800 | J5: 2025 | K5: 2250
A6: Simulation (20%) | B6: 300 | C6: 600 | D6: 900 | E6: 1200 | F6: 1500 | G6: 1800 | H6: 2100 | I6: 2400 | J6: 2700 | K6: 3000
A7: Pharma-Sponsored (20%) | B7: 300 | C7: 600 | D7: 900 | E7: 1200 | F7: 1500 | G7: 1800 | H7: 2100 | I7: 2400 | J7: 2700 | K7: 3000
A8: Conference (10%) | B8: 150 | C8: 300 | D8: 450 | E8: 600 | F8: 750 | G8: 900 | H8: 1050 | I8: 1200 | J8: 1350 | K8: 1500
A9: Certification (5%) | B9: 75 | C9: 150 | D9: 225 | E9: 300 | F9: 375 | G9: 450 | H9: 525 | I9: 600 | J9: 675 | K9: 750
A10: TOTAL REVENUE | B10: =SUM(B4:B9) -> 1500 | C10: =SUM(C4:C9) -> 3000 | D10: =SUM(D4:D9) -> 4500 | E10: =SUM(E4:E9) -> 6000 | F10: =SUM(F4:F9) -> 7500 | G10: =SUM(G4:G9) -> 9000 | H10: =SUM(H4:H9) -> 10500 | I10: =SUM(I4:I9) -> 12000 | ... K10: =SUM(K4:K9) -> 15000
A12: Headcount | B12: 10 | C12: 20 | D12: 35 | E12: 50 | F12: 60 | G12: 72 | H12: 85 | I12: 95 | J12: 105 | K12: 115
A13: Revenue per Employee | B13: =B10/B12 -> 150 | C13: =C10/C12 -> 150 | D13: =D10/D12 -> 128.57143 | E13: =E10/E12 -> 120 | F13: =F10/F12 -> 125 | G13: =G10/G12 -> 125 | H13: =H10/H12 -> 123.52941 | I13: =I10/I12 -> 126.31579 | ... K13: =K10/K12 -> 130.43478

Sheet Cost Structure
A1: COST STRUCTURE ANALYSIS
A3: Income Statement ($000s) | B3: Y1 | C3: Y2 | D3: Y3 | E3: Y4 | F3: Y5 | G3: Y6 | H3: Y7 | I3: Y8 | J3: Y9 | K3: Y10
A4: Revenue | B4: ='Revenue Model'!B10 -> 1500 | C4: ='Revenue Model'!C10 -> 3000 | D4: ='Revenue Model'!D10 -> 4500 | E4: ='Revenue Model'!E10 -> 6000 | F4: ='Revenue Model'!F10 -> 7500 | G4: ='Revenue Model'!G10 -> 9000 | H4: ='Revenue Model'!H10 -> 10500 | I4: ='Revenue Model'!I10 -> 12000 | ... K4: ='Revenue Model'!K10 -> 15000
A5: COGS (28%) | B5: =B4*0.28 -> 420 | C5: =C4*0.28 -> 840 | D5: =D4*0.28 -> 1260 | E5: =E4*0.28 -> 1680 | F5: =F4*0.28 -> 2100 | G5: =G4*0.28 -> 2520 | H5: =H4*0.28 -> 2940 | I5: =I4*0.28 -> 3360 | ... K5: =K4*0.28 -> 4200
A6: Gross Profit | B6: =B4-B5 -> 1080 | C6: =C4-C5 -> 2160 | D6: =D4-D5 -> 3240 | E6: =E4-E5 -> 4320 | F6: =F4-F5 -> 5400 | G6: =G4-G5 -> 6480 | H6: =H4-H5 -> 7560 | I6: =I4-I5 -> 8640 | ... K6: =K4-K5 -> 10800
A7: Gross Margin % | B7: =B6/B4 -> 0.72 | C7: =C6/C4 -> 0.72 | D7: =D6/D4 -> 0.72 | E7: =E6/E4 -> 0.72 | F7: =F6/F4 -> 0.72 | G7: =G6/G4 -> 0.72 | H7: =H6/H4 -> 0.72 | I7: =I6/I4 -> 0.72 | ... K7: =K6/K4 -> 0.72
A9: OpEx Components
A10: Content Development | B10: =B4*0.18 -> 270 | C10: =C4*0.16 -> 480 | D10: =D4*0.14 -> 630 | E10: =E4*0.12 -> 720 | F10: =F4*0.1 -> 750 | G10: =G4*0.09 -> 810 | H10: =H4*0.08 -> 840 | I10: =I4*0.08 -> 960 | J10: =J4*0.08 -> 1080 | K10: =K4*0.08 -> 1200
A11: Technology | B11: =B4*0.15 -> 225 | C11: =C4*0.14 -> 420 | D11: =D4*0.13 -> 585 | E11: =E4*0.12 -> 720 | F11: =F4*0.1 -> 750 | G11: =G4*0.09 -> 810 | H11: =H4*0.08 -> 840 | I11: =I4*0.08 -> 960 | J11: =J4*0.08 -> 1080 | K11: =K4*0.08 -> 1200
A12: Operations | B12: =B4*0.12 -> 180 | C12: =C4*0.11 -> 330 | D12: =D4*0.1 -> 450 | E12: =E4*0.09 -> 540 | F12: =F4*0.08 -> 600 | G12: =G4*0.07 -> 630 | H12: =H4*0.06 -> 630 | I12: =I4*0.06 -> 720 | J12: =J4*0.06 -> 810 | K12: =K4*0.06 -> 900
A13: Sales & Marketing | B13: =B4*0.1 -> 150 | C13: =C4*0.09 -> 270 | D13: =D4*0.08 -> 360 | E13: =E4*0.07 -> 420 | F13: =F4*0.06 -> 450 | G13: =G4*0.05 -> 450 | H13: =H4*0.04 -> 420 | I13: =I4*0.04 -> 480 | J13: =J4*0.04 -> 540 | K13: =K4*0.04 -> 600
A14: G&A | B14: =B4*0.05 -> 75 | C14: =C4*0.04 -> 120 | D14: =D4*0.04 -> 180 | E14: =E4*0.03 -> 180 | F14: =F4*0.03 -> 225 | G14: =G4*0.02 -> 180 | H14: =H4*0.02 -> 210 | I14: =I4*0.02 -> 240 | J14: =J4*0.02 -> 270 | K14: =K4*0.02 -> 300
A15: Total OpEx | B15: =SUM(B10:B14) -> 900 | C15: =SUM(C10:C14) -> 1620 | D15: =SUM(D10:D14) -> 2205 | E15: =SUM(E10:E14) -> 2580 | F15: =SUM(F10:F14) -> 2775 | G15: =SUM(G10:G14) -> 2880 | H15: =SUM(H10:H14) -> 2940 | I15: =SUM(I10:I14) -> 3360 | ... K15: =SUM(K10:K14) -> 4200

Sheet EBITDA & Cash Flow
A1: EBITDA & CASH FLOW ANALYSIS
A3: Income Statement ($000s) | B3: Y1 | C3: Y2 | D3: Y3 | E3: Y4 | F3: Y5 | G3: Y6 | H3: Y7 | I3: Y8 | J3: Y9 | K3: Y10
A4: Revenue | B4: ='Cost Structure'!B4 -> 1500 | C4: ='Cost Structure'!C4 -> 3000 | D4: ='Cost Structure'!D4 -> 4500 | E4: ='Cost Structure'!E4 -> 6000 | F4: ='Cost Structure'!F4 -> 7500 | G4: ='Cost Structure'!G4 -> 9000 | H4: ='Cost Structure'!H4 -> 10500 | I4: ='Cost Structure'!I4 -> 12000 | ... K4: ='Cost Structure'!K4 -> 15000
A5: COGS | B5: ='Cost Structure'!B5 -> 420 | C5: ='Cost Structure'!C5 -> 840 | D5: ='Cost Structure'!D5 -> 1260 | E5: ='Cost Structure'!E5 -> 1680 | F5: ='Cost Structure'!F5 -> 2100 | G5: ='Cost Structure'!G5 -> 2520 | H5: ='Cost Structure'!H5 -> 2940 | I5: ='Cost Structure'!I5 -> 3360 | ... K5: ='Cost Structure'!K5 -> 4200
A6: Gross Profit | B6: =B4-B5 -> 1080 | C6: =C4-C5 -> 2160 | D6: =D4-D5 -> 3240 | E6: =E4-E5 -> 4320 | F6: =F4-F5 -> 5400 | G6: =G4-G5 -> 6480 | H6: =H4-H5 -> 7560 | I6: =I4-I5 -> 8640 | ... K6: =K4-K5 -> 10800
A7: Operating Expenses | B7: ='Cost Structure'!B15 -> 900 | C7: ='Cost Structure'!C15 -> 1620 | D7: ='Cost Structure'!D15 -> 2205 | E7: ='Cost Structure'!E15 -> 2580 | F7: ='Cost Structure'!F15 -> 2775 | G7: ='Cost Structure'!G15 -> 2880 | H7: ='Cost Structure'!H15 -> 2940 | I7: ='Cost Structure'!I15 -> 3360 | ... K7: ='Cost Structure'!K15 -> 4200
A8: EBITDA | B8: =B6-B7 -> 180 | C8: =C6-C7 -> 540 | D8: =D6-D7 -> 1035 | E8: =E6-E7 -> 1740 | F8: =F6-F7 -> 2625 | G8: =G6-G7 -> 3600 | H8: =H6-H7 -> 4620 | I8: =I6-I7 -> 5280 | ... K8: =K6-K7 -> 6600
A9: EBITDA Margin % | B9: =B8/B4 -> 0.12 | C9: =C8/C4 -> 0.18 | D9: =D8/D4 -> 0.23 | E9: =E8/E4 -> 0.29 | F9: =F8/F4 -> 0.35 | G9: =G8/G4 -> 0.4 | H9: =H8/H4 -> 0.44 | I9: =I8/I4 -> 0.44 | ... K9: =K8/K4 -> 0.44

Sheet Capital Requirements
A1: CAPITAL REQUIREMENTS & INVESTMENT
A3: Investment Schedule
A4: Phase | B4: Amount ($) | C4: Timing
A5: Seed Development | B5: 500000 | C5: Year 1
A6: Platform Growth | B6: 500000 | C6: Year 2
A7: TOTAL INVESTMENT | B7: =B5+B6 -> 1000000

Sheet Valuation Scenarios
A1: VALUATION & EXIT ANALYSIS
A3: YEAR 5 EXIT VALUATION
A4: Metric | B4: Conservative | C4: Base Case | D4: Optimistic
A5: Year 5 EBITDA ($000s) | B5: ='EBITDA & Cash Flow'!F8 -> 2625 | C5: ='EBITDA & Cash Flow'!F8 -> 2625 | D5: ='EBITDA & Cash Flow'!F8 -> 2625
A6: EBITDA Multiple | B6: 8 | C6: 9 | D6: 10
A7: Enterprise Value ($000s) | B7: =B5*B6 -> 21000 | C7: =C5*C6 -> 23625 | D7: =D5*D6 -> 26250
A9: RETURN ANALYSIS
A10: Metric | B10: Conservative | C10: Base Case | D10: Optimistic
A11: Initial Investment ($000s) | B11: 1000 | C11: 1000 | D11: 1000
A12: Exit Value ($000s) | B12: =B7 -> 21000 | C12: =C7 -> 23625 | D12: =D7 -> 26250
A13: MOIC | B13: =B12/B11 -> 21 | C13: =C12/B11 -> 23.625 | D13: =D12/B11 -> 26.25

Sheet Assumptions
A1: MODEL ASSUMPTIONS
A3: Revenue Streams
A4: Institutional LMS | B4: 30%
A5: CME Subscriptions | B5: 15%
A6: Simulation Programs | B6: 20%
A7: Pharma-Sponsored | B7: 20%
A8: Conference Programs | B8: 10%
A9: Certification | B9: 5%
A11: Cost Structure
A12: COGS % | B12: 28%
A13: Gross Margin | B13: 72%
A15: Key Metrics
A16: Total Capital Required | B16: $1,000,000
A17: Y1 Revenue | B17: $1,500,000
A18: Y5 Revenue | B18: $28,000,000
A19: Y5 EBITDA Margin | B19: 46%
A20: Y5 Headcount | B20: 60
