Workbook

Sheet Executive Summary
A1: TKG - THEEB KNOWLEDGE GROUP
A2: Consolidated 5-Year Financial Model (SAR Thousands) - Conservative
A4: Metric | B4: 2026 | C4: 2027 | D4: 2028 | E4: 2029 | F4: 2030
A5: REVENUE BY ENTITY
A6: Waraqa (TKG-01) | B6: ='Waraqa (TKG-01)'!B12 | C6: ='Waraqa (TKG-01)'!C12 | D6: ='Waraqa (TKG-01)'!D12 | E6: ='Waraqa (TKG-01)'!E12 | F6: ='Waraqa (TKG-01)'!F12
A7: Nama CRO (TKG-02) | B7: ='Nama CRO (TKG-02)'!B10 | C7: ='Nama CRO (TKG-02)'!C10 | D7: ='Nama CRO (TKG-02)'!D10 | E7: ='Nama CRO (TKG-02)'!E10 | F7: ='Nama CRO (TKG-02)'!F10
A8: Nama Academy (TKG-03) | B8: ='Nama Academy (TKG-03)'!B10 | C8: ='Nama Academy (TKG-03)'!C10 | D8: ='Nama Academy (TKG-03)'!D10 | E8: ='Nama Academy (TKG-03)'!E10 | F8: ='Nama Academy (TKG-03)'!F10
A9: Nama Bio (TKG-04) | B9: ='Nama Bio (TKG-04)'!B5 | C9: ='Nama Bio (TKG-04)'!C5 | D9: ='Nama Bio (TKG-04)'!D5 | E9: ='Nama Bio (TKG-04)'!E5 | F9: ='Nama Bio (TKG-04)'!F5
A10: Saudi Evidence (TKG-05) | B10: ='Saudi Evidence (TKG-05)'!B8 | C10: ='Saudi Evidence (TKG-05)'!C8 | D10: ='Saudi Evidence (TKG-05)'!D8 | E10: ='Saudi Evidence (TKG-05)'!E8 | F10: ='Saudi Evidence (TKG-05)'!F8
A11: TOTAL TKG REVENUE | B11: =SUM(B6:B10) | C11: =SUM(C6:C10) | D11: =SUM(D6:D10) | E11: =SUM(E6:E10) | F11: =SUM(F6:F10)
A13: EBITDA BY ENTITY
A14: Waraqa (TKG-01) | B14: ='Waraqa (TKG-01)'!B17 | C14: ='Waraqa (TKG-01)'!C17 | D14: ='Waraqa (TKG-01)'!D17 | E14: ='Waraqa (TKG-01)'!E17 | F14: ='Waraqa (TKG-01)'!F17
A15: Nama CRO (TKG-02) | B15: ='Nama CRO (TKG-02)'!B15 | C15: ='Nama CRO (TKG-02)'!C15 | D15: ='Nama CRO (TKG-02)'!D15 | E15: ='Nama CRO (TKG-02)'!E15 | F15: ='Nama CRO (TKG-02)'!F15
A16: Nama Academy (TKG-03) | B16: ='Nama Academy (TKG-03)'!B15 | C16: ='Nama Academy (TKG-03)'!C15 | D16: ='Nama Academy (TKG-03)'!D15 | E16: ='Nama Academy (TKG-03)'!E15 | F16: ='Nama Academy (TKG-03)'!F15
A17: Nama Bio (TKG-04) | B17: ='Nama Bio (TKG-04)'!B10 | C17: ='Nama Bio (TKG-04)'!C10 | D17: ='Nama Bio (TKG-04)'!D10 | E17: ='Nama Bio (TKG-04)'!E10 | F17: ='Nama Bio (TKG-04)'!F10
A18: Saudi Evidence (TKG-05) | B18: ='Saudi Evidence (TKG-05)'!B13 | C18: ='Saudi Evidence (TKG-05)'!C13 | D18: ='Saudi Evidence (TKG-05)'!D13 | E18: ='Saudi Evidence (TKG-05)'!E13 | F18: ='Saudi Evidence (TKG-05)'!F13
A19: TOTAL TKG EBITDA | B19: =SUM(B14:B18) | C19: =SUM(C14:C18) | D19: =SUM(D14:D18) | E19: =SUM(E14:E18) | F19: =SUM(F14:F18)
A20: TKG EBITDA Margin % | B20: =IF(B11=0,0,B19/B11) | C20: =IF(C11=0,0,C19/C11) | D20: =IF(D11=0,0,D19/D11) | E20: =IF(E11=0,0,E19/E11) | F20: =IF(F11=0,0,F19/F11)
A22: HEADCOUNT BY ENTITY
A23: Waraqa | B23: ='Waraqa (TKG-01)'!B19 | C23: ='Waraqa (TKG-01)'!C19 | D23: ='Waraqa (TKG-01)'!D19 | E23: ='Waraqa (TKG-01)'!E19 | F23: ='Waraqa (TKG-01)'!F19
A24: Nama CRO | B24: ='Nama CRO (TKG-02)'!B17 | C24: ='Nama CRO (TKG-02)'!C17 | D24: ='Nama CRO (TKG-02)'!D17 | E24: ='Nama CRO (TKG-02)'!E17 | F24: ='Nama CRO (TKG-02)'!F17
A25: Nama Academy | B25: ='Nama Academy (TKG-03)'!B17 | C25: ='Nama Academy (TKG-03)'!C17 | D25: ='Nama Academy (TKG-03)'!D17 | E25: ='Nama Academy (TKG-03)'!E17 | F25: ='Nama Academy (TKG-03)'!F17
A26: Nama Bio | B26: ='Nama Bio (TKG-04)'!B12 | C26: ='Nama Bio (TKG-04)'!C12 | D26: ='Nama Bio (TKG-04)'!D12 | E26: ='Nama Bio (TKG-04)'!E12 | F26: ='Nama Bio (TKG-04)'!F12
A27: Saudi Evidence | B27: ='Saudi Evidence (TKG-05)'!B15 | C27: ='Saudi Evidence (TKG-05)'!C15 | D27: ='Saudi Evidence (TKG-05)'!D15 | E27: ='Saudi Evidence (TKG-05)'!E15 | F27: ='Saudi Evidence (TKG-05)'!F15
A28: TOTAL TKG HEADCOUNT | B28: =SUM(B23:B27) | C28: =SUM(C23:C27) | D28: =SUM(D23:D27) | E28: =SUM(E23:E27) | F28: =SUM(F23:F27)
A30: CAPITAL REQUIREMENTS (SAR '000)
A31: Nama CRO (Alfaisaliah) | B31: 9375 | C31: 7500 | D31: 1875 | E31: 0 | F31: 0
A32: Nama Bio (Grant+Equity) | B32: 6206 | C32: 1400 | D32: 1150 | E32: 0 | F32: 0
A33: Saudi Evidence (Grants) | B33: 3000 | C33: 4000 | D33: 3000 | E33: 0 | F33: 0
A34: Waraqa (Self-funded) | B34: 0 | C34: 0 | D34: 0 | E34: 0 | F34: 0
A35: Nama Academy (Waraqa) | B35: 400 | C35: 400 | D35: 500 | E35: 500 | F35: 500
A36: TOTAL CAPITAL REQUIRED | B36: =SUM(B31:B35) | C36: =SUM(C31:C35) | D36: =SUM(D31:D35) | E36: =SUM(E31:E35) | F36: =SUM(F31:F35)

Sheet Waraqa (TKG-01)
A1: Waraqa Publishing (TKG-01) - SAR '000 | B1: 2026 | C1: 2027 | D1: 2028 | E1: 2029 | F1: 2030
A2: REVENUE STREAMS
A3: 1. Society Journal Publishing | B3: 234 | C3: 860 | D3: 3600 | E3: 5400 | F3: 7200
A4: 2. University Preprint Platform | B4: 24 | C4: 200 | D4: 1500 | E4: 2500 | F4: 3500
A5: 3. Funded Journal Operations | B5: 360 | C5: 480 | D5: 650 | E5: 700 | F5: 750
A6: 4. Research Integrity Services | B6: 360 | C6: 800 | D6: 1800 | E6: 2700 | F6: 3500
A7: 5. Conference Proceedings | B7: 240 | C7: 500 | D7: 1200 | E7: 1800 | F7: 2400
A8: 6. Ecosystem Cross-Group Revenue | B8: 100 | C8: 300 | D8: 700 | E8: 1000 | F8: 1500
A9: 7. AI Content Licensing | B9: 0 | C9: 500 | D9: 2000 | E9: 4000 | F9: 7000
A10: 8. PubHelper Service Revenue | B10: 400 | C10: 800 | D10: 1500 | E10: 2500 | F10: 3500
A11: 9. Physician Reputation Platform | B11: 200 | C11: 1200 | D11: 3000 | E11: 5000 | F11: 7000
A12: TOTAL REVENUE | B12: =SUM(B3:B11) | C12: =SUM(C3:C11) | D12: =SUM(D3:D11) | E12: =SUM(E3:E11) | F12: =SUM(F3:F11)
A13: COST STRUCTURE
A14: COGS | B14: 800 | C14: 1500 | D14: 3500 | E14: 5500 | F14: 7500
A15: G&A | B15: 600 | C15: 800 | D15: 1200 | E15: 1500 | F15: 1800
A16: S&M | B16: 200 | C16: 350 | D16: 500 | E16: 700 | F16: 900
A17: EBITDA | B17: =B12-B14-B15-B16 | C17: =C12-C14-C15-C16 | D17: =D12-D14-D15-D16 | E17: =E12-E14-E15-E16 | F17: =F12-F14-F15-F16
A18: EBITDA Margin % | B18: =IF(B12=0,0,B17/B12) | C18: =IF(C12=0,0,C17/C12) | D18: =IF(D12=0,0,D17/D12) | E18: =IF(E12=0,0,E17/E12) | F18: =IF(F12=0,0,F17/F12)
A19: Headcount | B19: 8 | C19: 15 | D19: 25 | E19: 35 | F19: 45
A20: Nama Academy Allocation | B20: -400 | C20: -400 | D20: -500 | E20: -500 | F20: -500

Sheet Nama CRO (TKG-02)
A1: Nama CRO / Medical (TKG-02) - SAR '000 | B1: 2026 | C1: 2027 | D1: 2028 | E1: 2029 | F1: 2030
A2: REVENUE STREAMS
A3: 1. Interventional Trials (Phase I-IV) | B3: 1500 | C3: 4500 | D3: 9000 | E3: 15000 | F3: 22500
A4: 2. RWE & Observational Studies | B4: 750 | C4: 2250 | D4: 4500 | E4: 7500 | F4: 11250
A5: 3. CTU Development Contracts | B5: 500 | C5: 1200 | D5: 2000 | E5: 3000 | F5: 4000
A6: 4. SMO Services | B6: 375 | C6: 750 | D6: 1500 | E6: 2250 | F6: 3000
A7: 5. Training & Capability Building | B7: 200 | C7: 500 | D7: 1000 | E7: 1500 | F7: 2000
A8: 6. Medical Writing (inter-company) | B8: 300 | C8: 450 | D8: 600 | E8: 750 | F8: 900
A9: TOTAL REVENUE | B9: =SUM(B3:B8) | C9: =SUM(C3:C8) | D9: =SUM(D3:D8) | E9: =SUM(E3:E8) | F9: =SUM(F3:F8)
A10: COST STRUCTURE
A11: COGS | B11: 2200 | C11: 5500 | D11: 10500 | E11: 16000 | F11: 22000
A12: G&A | B12: 1200 | C12: 1500 | D12: 2000 | E12: 2500 | F12: 3000
A13: S&M | B13: 300 | C13: 500 | D13: 800 | E13: 1000 | F13: 1200
A14: EBITDA | B14: =B9-B11-B12-B13 | C14: =C9-C11-C12-C13 | D14: =D9-D11-D12-D13 | E14: =E9-E11-E12-E13 | F14: =F9-F11-F12-F13
A15: EBITDA Margin % | B15: =IF(B9=0,0,B14/B9) | C15: =IF(C9=0,0,C14/C9) | D15: =IF(D9=0,0,D14/D9) | E15: =IF(E9=0,0,E14/E9) | F15: =IF(F9=0,0,F14/F9)
A16: Headcount | B16: 20 | C16: 35 | D16: 55 | E16: 80 | F16: 110
A18: INVESTMENT
A19: Alfaisaliah Investment (SAR '000) | B19: 9375 | C19: 7500 | D19: 1875 | E19: 0 | F19: 0
A20: Alfaisaliah Equity | B20: 25-35%

Sheet Nama Academy (TKG-03)
A1: Nama Academy (TKG-03) - SAR '000 | B1: 2026 | C1: 2027 | D1: 2028 | E1: 2029 | F1: 2030
A2: REVENUE STREAMS
A3: 1. SHA Life Support (BLS/ACLS/PALS) | B3: 800 | C3: 1800 | D3: 3500 | E3: 5500 | F3: 8000
A4: 2. CME Programs (Specialty) | B4: 400 | C4: 1000 | D4: 2500 | E4: 4000 | F4: 6000
A5: 3. Academy-as-a-Service (AaaS) | B5: 0 | C5: 500 | D5: 1500 | E5: 3000 | F5: 5000
A6: 4. Conference & Society CME | B6: 300 | C6: 800 | D6: 1500 | E6: 2500 | F6: 3500
A7: 5. MGA Bundle CME Revenue Share | B7: 0 | C7: 200 | D7: 600 | E7: 1200 | F7: 2000
A8: 6. HRDF/Tamheer Programs | B8: 200 | C8: 400 | D8: 700 | E8: 1000 | F8: 1500
A9: TOTAL REVENUE | B9: =SUM(B3:B8) | C9: =SUM(C3:C8) | D9: =SUM(D3:D8) | E9: =SUM(E3:E8) | F9: =SUM(F3:F8)
A10: COST STRUCTURE
A11: COGS | B11: 1100 | C11: 2500 | D11: 5000 | E11: 8000 | F11: 12000
A12: G&A | B12: 500 | C12: 700 | D12: 1000 | E12: 1300 | F12: 1600
A13: S&M | B13: 150 | C13: 300 | D13: 500 | E13: 700 | F13: 900
A14: EBITDA | B14: =B9-B11-B12-B13 | C14: =C9-C11-C12-C13 | D14: =D9-D11-D12-D13 | E14: =E9-E11-E12-E13 | F14: =F9-F11-F12-F13
A15: EBITDA Margin % | B15: =IF(B9=0,0,B14/B9) | C15: =IF(C9=0,0,C14/C9) | D15: =IF(D9=0,0,D14/D9) | E15: =IF(E9=0,0,E14/E9) | F15: =IF(F9=0,0,F14/F9)
A16: Headcount | B16: 10 | C16: 18 | D16: 30 | E16: 45 | F16: 60
A17: Funded by: Waraqa (SAR 400-500K/yr)

Sheet Nama Bio (TKG-04)
A1: Nama Bio Center (TKG-04) - SAR '000 | B1: 2026 | C1: 2027 | D1: 2028 | E1: 2029 | F1: 2030
A2: REVENUE
A3: 1. Bioequivalence Studies | B3: 2700 | C3: 4500 | D3: 8100 | E3: 10238 | F3: 13650
A4: 2. Training & Capacity Building | B4: 0 | C4: 0 | D4: 0 | E4: 0 | F4: 0
A5: TOTAL REVENUE | B5: =SUM(B3:B4) | C5: =SUM(C3:C4) | D5: =SUM(D3:D4) | E5: =SUM(E3:E4) | F5: =SUM(F3:F4)
A6: COST STRUCTURE
A7: COGS | B7: 1872 | C7: 4479 | D7: 8220 | E7: 10378 | F7: 13433
A8: G&A | B8: 2048 | C8: 2151 | D8: 3084 | E8: 3238 | F8: 3400
A9: S&M | B9: 80 | C9: 232 | D9: 501 | E9: 526 | F9: 553
A10: EBITDA | B10: =B5-B7-B8-B9 | C10: =C5-C7-C8-C9 | D10: =D5-D7-D8-D9 | E10: =E5-E7-E8-E9 | F10: =F5-F7-F8-F9
A11: EBITDA Margin % | B11: =IF(B5=0,0,B10/B5) | C11: =IF(C5=0,0,C10/C5) | D11: =IF(D5=0,0,D10/D5) | E11: =IF(E5=0,0,E10/E5) | F11: =IF(F5=0,0,F10/F5)
A12: Headcount | B12: 12 | C12: 18 | D12: 28 | E12: 35 | F12: 42
A13: CAPITAL
A14: Capex | B14: 5000 | C14: 1400 | D14: 1150 | E14: 0 | F14: 0
A15: Govt Grant: SAR 2,000K | Equity: SAR 6,206K
A16: BE Studies/Year | B16: 10 | C16: 15 | D16: 25 | E16: 30 | F16: 40

Sheet Saudi Evidence (TKG-05)
A1: Saudi Evidence Platform (TKG-05) - SAR '000 | B1: 2026 | C1: 2027 | D1: 2028 | E1: 2029 | F1: 2030
A2: REVENUE STREAMS
A3: 1. CHI Partnership / Govt Contract | B3: 0 | C3: 500 | D3: 2000 | E3: 4000 | F3: 7000
A4: 2. Institutional Subscriptions (B2B) | B4: 0 | C4: 300 | D4: 1500 | E4: 3500 | F4: 7000
A5: 3. Pharma Data Packages | B5: 0 | C5: 0 | D5: 500 | E5: 1500 | F5: 3000
A6: 4. CME Platform Fees | B6: 0 | C6: 200 | D6: 800 | E6: 1500 | F6: 2500
A7: TOTAL REVENUE | B7: =SUM(B3:B6) | C7: =SUM(C3:C6) | D7: =SUM(D3:D6) | E7: =SUM(E3:E6) | F7: =SUM(F3:F6)
A8: COST STRUCTURE
A9: COGS (Cloud, APIs, DeepEvidence) | B9: 500 | C9: 800 | D9: 1500 | E9: 2500 | F9: 4000
A10: G&A (Dev Team, Ops) | B10: 2000 | C10: 2500 | D10: 3000 | E10: 3500 | F10: 4000
A11: S&M | B11: 200 | C11: 400 | D11: 600 | E11: 800 | F11: 1000
A12: EBITDA | B12: =B7-B9-B10-B11 | C12: =C7-C9-C10-C11 | D12: =D7-D9-D10-D11 | E12: =E7-E9-E10-E11 | F12: =F7-F9-F10-F11
A13: EBITDA Margin % | B13: =IF(B7=0,0,B12/B7) | C13: =IF(C7=0,0,C12/C7) | D13: =IF(D7=0,0,D12/D7) | E13: =IF(E7=0,0,E12/E7) | F13: =IF(F7=0,0,F12/F7)
A14: Headcount | B14: 6 | C14: 10 | D14: 15 | E14: 20 | F14: 25
A15: Active Users (Clinicians) | B15: 500 | C15: 2000 | D15: 10000 | E15: 30000 | F15: 75000
A16: FUNDING (NON-DILUTIVE)
A17: Government Grants (SDAIA/RDIA/NTDP) | B17: 3000 | C17: 4000 | D17: 3000 | E17: 0 | F17: 0

Sheet Assumptions
A1: Assumption | B1: Value | C1: Basis
A2: Currency | B2: SAR (thousands) | C2: All figures in SAR thousands
A3: Exchange Rate | B3: 1 USD = 3.75 SAR | C3: SAMA
A4: Tax/Zakat | B4: 2.5% | C4: Saudi Zakat on local entities
A5: Discount Rate | B5: 15% | C5: Emerging market healthcare premium
A6: Terminal Growth | B6: 3% | C6: GDP-aligned long-term
A7: Scenario | B7: Conservative | C7: 25-35% below management base case
A9: MARKET
A10: Healthcare Spend | B10: SAR 196B/year | C10: MOH / Vision 2030
A11: Scientific Societies | B11: 80+ | C11: SCFHS registered
A12: CME Mandate | B12: 30 credits/year | C12: SCFHS regulation
A13: Licensed Professionals | B13: 300,000+ | C13: SCFHS registry
A14: Private Hospitals | B14: 400+ | C14: MOH statistics
A16: OPERATIONAL
A17: Society Partnerships | B17: 3>5>10>15>20 (Y1-Y5) | C17: Conversion rate model
A18: Physician Pipeline | B18: 500>1K>2K>3.5K>5K | C18: Academy capacity
A19: BE Studies/Year | B19: 10>15>25>30>40 | C19: CARE ward capacity
A20: CRO Active Trials | B20: 5>12>20>30>40 | C20: Alfaisaliah + external
A21: Saudi Evidence Users | B21: 500>2K>10K>30K>75K | C21: Free adoption curve
A23: PRICING
A24: APC per article | B24: SAR 3,000-4,000 | C24: Int'l OA competitive
A25: BE Study Price | B25: SAR 300-450K | C25: Market rate KSA
A26: CRO Trial Revenue | B26: SAR 750K-1.5M/study | C26: Phase-dependent
A27: SHA Course Fee | B27: SAR 600-1,500/person | C27: SHA standard
A28: AaaS Contract | B28: SAR 200-500K/year | C28: Hospital size dependent
A29: Physician Plan | B29: SAR 2-15K/month | C29: 3-tier subscription
