Workbook
Name _inflation: [1]Assumptions!$C$118
Name day_in_year: Input!$C$100
Name Depreciation_T: [1]Assumptions!$C$116
Name start_year: Input!$C$4

Sheet Input
B1: Input
I3: Input cell
B4: Start Year | C4: 2024
I5: Calculation cell
B7: Scenario Summary
B10: volumes/year | C10: =start_year -> 2024 | D10: =C10+1 -> 2025 | E10: =D10+1 -> 2026 | F10: =E10+1 -> 2027 | G10: =F10+1 -> 2028 | H10: =G10+1 -> 2029
B11: =B106 -> Peer Reveiwed Manuscript | C11: =$C$109*(1+$D$109)^(C10-start_year) -> 50 | D11: =$C$109*(1+$D$109)^(D10-start_year) -> 57.5 | E11: =$C$109*(1+$D$109)^(E10-start_year) -> 66.125 | F11: =$C$109*(1+$D$109)^(F10-start_year) -> 76.04375 | G11: =$C$109*(1+$D$109)^(G10-start_year) -> 87.450312 | H11: =$C$109*(1+$D$109)^(H10-start_year) -> 100.56786
B13: Sale Prices
B14: in SAR | C14: =start_year -> 2024 | D14: =C14+1 -> 2025 | E14: =D14+1 -> 2026 | F14: =E14+1 -> 2027 | G14: =F14+1 -> 2028 | H14: =G14+1 -> 2029
B15: =B106 -> Peer Reveiwed Manuscript | C15: =$C$106*(1+$D$106)^(C14-start_year) -> 93750 | D15: =$C$106*(1+$D$106)^(D14-start_year) -> 96562.5 | E15: =$C$106*(1+$D$106)^(E14-start_year) -> 99459.375 | F15: =$C$106*(1+$D$106)^(F14-start_year) -> 102443.16 | G15: =$C$106*(1+$D$106)^(G14-start_year) -> 105516.45 | H15: =$C$106*(1+$D$106)^(H14-start_year) -> 108681.94
B18: volumes/year | C18: =start_year -> 2024 | D18: =C18+1 -> 2025 | E18: =D18+1 -> 2026 | F18: =E18+1 -> 2027 | G18: =F18+1 -> 2028 | H18: =G18+1 -> 2029
B19: =B106 -> Peer Reveiwed Manuscript | C19: =$C$115*(1+$D$115)^(C18-start_year) -> 50 | D19: =$C$115*(1+$D$115)^(D18-start_year) -> 57.5 | E19: =$C$115*(1+$D$115)^(E18-start_year) -> 66.125 | F19: =$C$115*(1+$D$115)^(F18-start_year) -> 76.04375 | G19: =$C$115*(1+$D$115)^(G18-start_year) -> 87.450312 | H19: =$C$115*(1+$D$115)^(H18-start_year) -> 100.56786
B22: in SAR | C22: =start_year -> 2024 | D22: =C22+1 -> 2025 | E22: =D22+1 -> 2026 | F22: =E22+1 -> 2027 | G22: =F22+1 -> 2028 | H22: =G22+1 -> 2029
B23: =B106 -> Peer Reveiwed Manuscript | C23: =$C$112*(1+$D$112)^(C22-start_year) -> 18800 | D23: =$C$112*(1+$D$112)^(D22-start_year) -> 19364 | E23: =$C$112*(1+$D$112)^(E22-start_year) -> 19944.92 | F23: =$C$112*(1+$D$112)^(F22-start_year) -> 20543.268 | G23: =$C$112*(1+$D$112)^(G22-start_year) -> 21159.566 | H23: =$C$112*(1+$D$112)^(H22-start_year) -> 21794.353
B25: General Input
B27: Working capital | C27: =start_year -> 2024 | D27: =C27+1 -> 2025 | E27: =D27+1 -> 2026 | F27: =E27+1 -> 2027 | G27: =F27+1 -> 2028 | H27: =G27+1 -> 2029
B28: Days payable (G&A) | C28: 30 | D28: 30 | E28: 30 | F28: 30 | G28: 30 | H28: 30
B29: Days payable (S&M) | C29: 30 | D29: 30 | E29: 30 | F29: 30 | G29: 30 | H29: 30
B30: Days payable (COGS) | C30: 30 | D30: 30 | E30: 30 | F30: 30 | G30: 30 | H30: 30
B31: Days receivable | C31: 120 | D31: 120 | E31: 120 | F31: 120 | G31: 120 | H31: 120
B32: Days inventory | C32: 30 | D32: 30 | E32: 30 | F32: 30 | G32: 30 | H32: 30
B34: Manpower Count | C34: =start_year -> 2024 | D34: =C34+1 -> 2025 | E34: =D34+1 -> 2026 | F34: =E34+1 -> 2027 | G34: =F34+1 -> 2028 | H34: =G34+1 -> 2029
B35: G & A
B36: CEO ( Journal Manager) | C36: 1 | D36: 1 | E36: 1 | F36: 1 | G36: 1 | H36: 1
B37: Admin Staff (Except S&M) | C37: 3 | D37: 3 | E37: 3 | F37: 3 | G37: 3 | H37: 3
B38: Other support ( Lawyer, Bioethicist) | C38: 2 | D38: 2 | E38: 2 | F38: 2 | G38: 2 | H38: 2
B39: S & M
B40: S & M staff | C40: 2 | D40: 3 | E40: 3 | F40: 3 | G40: 3 | H40: 3
B41: Direct Labor
B42: Editor in Chief | C42: 2 | D42: 2 | E42: 2 | F42: 2 | G42: 2 | H42: 2
B43: Coordinator | C43: 2 | D43: 2 | E43: 2 | F43: 2 | G43: 2 | H43: 2
B44: Language Editor | C44: 2 | D44: 2 | E44: 2 | F44: 2 | G44: 2 | H44: 2
B46: Manpower Cost | C46: Base Comp. | D46: Benefits | E46: Total Comp | G46: Base Comp. | H46: Benefits | I46: Total Comp
B47: Yearly Comp (SAR/year)
B48: =B35 -> G & A
B49: =B36 -> CEO ( Journal Manager) | C49: =G49*$F$52 -> 420000 | D49: =H49*$F$52 -> 180000 | E49: =SUM(C49:D49) -> 600000 | G49: 35000 | H49: 15000 | I49: =SUM(G49:H49) -> 50000
B50: =B37 -> Admin Staff (Except S&M) | C50: =G50*$F$52 -> 144000 | D50: =H50*$F$52 -> 66000 | E50: =SUM(C50:D50) -> 210000 | G50: 12000 | H50: 5500 | I50: =SUM(G50:H50) -> 17500
B51: =B38 -> Other support ( Lawyer, Bioethicist) | C51: =G51*$F$52 -> 144000 | D51: =H51*$F$52 -> 66000 | E51: =SUM(C51:D51) -> 210000 | G51: 12000 | H51: 5500 | I51: =SUM(G51:H51) -> 17500
B52: =B39 -> S & M | F52: 12
B53: =B40 -> S & M staff | C53: =G53*$F$52 -> 144000 | D53: =H53*$F$52 -> 66000 | E53: =SUM(C53:D53) -> 210000 | G53: 12000 | H53: 5500 | I53: =SUM(G53:H53) -> 17500
B54: =B41 -> Direct Labor
B55: =B42 -> Editor in Chief | C55: =G55*$F$52*0 -> 0 | D55: =H55*$F$52*0 -> 0 | E55: =SUM(C55:D55) -> 0 | G55: 35000 | H55: 15000 | I55: =SUM(G55:H55) -> 50000
B56: =B43 -> Coordinator | C56: =G56*$F$52 -> 144000 | D56: =H56*$F$52 -> 66000 | E56: =SUM(C56:D56) -> 210000 | G56: 12000 | H56: 5500 | I56: =SUM(G56:H56) -> 17500
B57: =B44 -> Language Editor | C57: =G57*$F$52 -> 240000 | D57: =H57*$F$52 -> 96000 | E57: =SUM(C57:D57) -> 336000 | G57: 20000 | H57: 8000 | I57: =SUM(G57:H57) -> 28000
B60: Annual Costs assumptions (in SAR/year)
C61: Fixed Annual Exp | D61: Variable Annual Exp | E61: Sources
B62: G&A (Non operating costs)
B63: Hiring Costs | C63: =10000*Manpower!C61 -> 140000
B64: S&M (Non operating costs)
B65: Supplies | C65: =100000*3.75 -> 375000
B66: Advertising | C66: =100000*3.76*2 -> 752000
B67: Travel | C67: =3*2*55000 -> 330000
B68: Commissions
B70: CAPEX
B72: Capital Expenditures ( SAR) | C72: =start_year-1 -> 2023 | D72: =start_year -> 2024 | E72: =D72+1 -> 2025 | F72: =E72+1 -> 2026 | G72: =F72+1 -> 2027 | H72: =G72+1 -> 2028
B73: Set up Expenses | C73: =100000*3.75 -> 375000
B74: Branding and identity | C74: =150000*3.75 -> 562500
B75: …
B76: Total Capex per year | C76: =SUM(C73:C75) -> 937500 | D76: =SUM(D73:D75) -> 0 | E76: =SUM(E73:E75) -> 0 | F76: =SUM(F73:F75) -> 0 | G76: =SUM(G73:G75) -> 0 | H76: =SUM(H73:H75) -> 0
B78: Total Project Cost | C78: =start_year-1 -> 2023
B79: Capital Expenditure | C79: =C76 -> 937500
B80: Working Capital | C80: ='Working Capital'!C12 -> 1520416.7
B81: Total Project Cost: | C81: =SUM(C79:C80) -> 2457916.7
B83: Financing
B85: Financing | C85: =start_year-1 -> 2023 | D85: =start_year -> 2024 | E85: =D85+1 -> 2025 | F85: =E85+1 -> 2026 | G85: =F85+1 -> 2027 | H85: =G85+1 -> 2028
B86: Hevolution | C86: =2550000 -> 2550000 | D86: =2550000 -> 2550000 | E86: 1250000 | F86: 750000
B87: Other Parties
B89: Others
B91: Other Assumptions
B93: Annual Increase in Salaries & Benefits | C93: 0.05
B94: Depreciation Period (Years) | C94: 10
B95: Grace period (principal) | C95: 1
B96: Loan installments | C96: 5
B97: Management fees | C97: 0.05
B98: Zakat | C98: 0.025
B99: Inflation | C99: 0.05
B100: Number of days in a year | C100: 360
B103: Scenario assumptions
B105: Sale Prices (in SAR/unit) | C105: =start_year -> 2024 | D105: Y to Y
B106: Peer Reveiwed Manuscript | C106: =3.75*25000 -> 93750 | D106: 0.03
B108: Sales Assumptions (in units) | C108: =start_year -> 2024 | D108: Y to Y
B109: =B106 -> Peer Reveiwed Manuscript | C109: 50 | D109: 0.15
B111: Subscription cost/ International Publisher (in SAR/unit) | C111: =start_year -> 2024 | D111: Y to Y
B112: =B106 -> Peer Reveiwed Manuscript | C112: =5000*3.76 -> 18800 | D112: 0.03
B114: =B108 -> Sales Assumptions (in units) | C114: =start_year -> 2024 | D114: Y to Y
B115: =B106 -> Peer Reveiwed Manuscript | C115: 50 | D115: 0.15

Sheet Revenues
B1: Revenues
C5: =start_year -> 2024 | D5: =C5+1 -> 2025 | E5: =D5+1 -> 2026 | F5: =E5+1 -> 2027 | G5: =F5+1 -> 2028 | H5: =G5+1 -> 2029
B6: =Input!B11 -> Peer Reveiwed Manuscript | C6: =Input!C11*Input!C15 -> 4687500 | D6: =Input!D11*Input!D15 -> 5552343.7 | E6: =Input!E11*Input!E15 -> 6576751.2 | F6: =Input!F11*Input!F15 -> 7790161.8 | G6: =Input!G11*Input!G15 -> 9227446.6 | H6: =Input!H11*Input!H15 -> 10929911
B8: Total sales revenues | C8: =SUM(C6:C6) -> 4687500 | D8: =SUM(D6:D6) -> 5552343.7 | E8: =SUM(E6:E6) -> 6576751.2 | F8: =SUM(F6:F6) -> 7790161.8 | G8: =SUM(G6:G6) -> 9227446.6 | H8: =SUM(H6:H6) -> 10929911

Sheet Manpower
B1: Manpower - Count & Compensation
C3: =start_year -> 2024 | D3: =C3+1 -> 2025 | E3: =D3+1 -> 2026 | F3: =E3+1 -> 2027 | G3: =F3+1 -> 2028 | H3: =G3+1 -> 2029
B4: G & A
B5: =Input!B49 -> CEO ( Journal Manager)
B6: Count | C6: =Input!C36 -> 1 | D6: =Input!D36 -> 1 | E6: =Input!E36 -> 1 | F6: =Input!F36 -> 1 | G6: =Input!G36 -> 1 | H6: =Input!H36 -> 1
B7: Compensation | C7: =Input!$E$49*(1+Input!$C$93)^(C$3-start_year) -> 600000 | D7: =Input!$E$49*(1+Input!$C$93)^(D$3-start_year) -> 630000 | E7: =Input!$E$49*(1+Input!$C$93)^(E$3-start_year) -> 661500 | F7: =Input!$E$49*(1+Input!$C$93)^(F$3-start_year) -> 694575 | G7: =Input!$E$49*(1+Input!$C$93)^(G$3-start_year) -> 729303.75 | H7: =Input!$E$49*(1+Input!$C$93)^(H$3-start_year) -> 765768.94
B8: Total Compensation | C8: =C6*C7 -> 600000 | D8: =D6*D7 -> 630000 | E8: =E6*E7 -> 661500 | F8: =F6*F7 -> 694575 | G8: =G6*G7 -> 729303.75 | H8: =H6*H7 -> 765768.94
B9: =Input!B37 -> Admin Staff (Except S&M)
B10: Count | C10: =Input!C37 -> 3 | D10: =Input!D37 -> 3 | E10: =Input!E37 -> 3 | F10: =Input!F37 -> 3 | G10: =Input!G37 -> 3 | H10: =Input!H37 -> 3
B11: Compensation | C11: =Input!$E$50*(1+Input!$C$93)^(C$3-start_year) -> 210000 | D11: =Input!$E$50*(1+Input!$C$93)^(D$3-start_year) -> 220500 | E11: =Input!$E$50*(1+Input!$C$93)^(E$3-start_year) -> 231525 | F11: =Input!$E$50*(1+Input!$C$93)^(F$3-start_year) -> 243101.25 | G11: =Input!$E$50*(1+Input!$C$93)^(G$3-start_year) -> 255256.31 | H11: =Input!$E$50*(1+Input!$C$93)^(H$3-start_year) -> 268019.13
B12: Total Compensation | C12: =C10*C11 -> 630000 | D12: =D10*D11 -> 661500 | E12: =E10*E11 -> 694575 | F12: =F10*F11 -> 729303.75 | G12: =G10*G11 -> 765768.94 | H12: =H10*H11 -> 804057.38
B13: =Input!B38 -> Other support ( Lawyer, Bioethicist)
B14: Count | C14: =Input!C38 -> 2 | D14: =Input!D38 -> 2 | E14: =Input!E38 -> 2 | F14: =Input!F38 -> 2 | G14: =Input!G38 -> 2 | H14: =Input!H38 -> 2
B15: Compensation | C15: =Input!$E$51*(1+Input!$C$93)^(C$3-start_year) -> 210000 | D15: =Input!$E$51*(1+Input!$C$93)^(D$3-start_year) -> 220500 | E15: =Input!$E$51*(1+Input!$C$93)^(E$3-start_year) -> 231525 | F15: =Input!$E$51*(1+Input!$C$93)^(F$3-start_year) -> 243101.25 | G15: =Input!$E$51*(1+Input!$C$93)^(G$3-start_year) -> 255256.31 | H15: =Input!$E$51*(1+Input!$C$93)^(H$3-start_year) -> 268019.13
B16: Total Compensation | C16: =C14*C15 -> 420000 | D16: =D14*D15 -> 441000 | E16: =E14*E15 -> 463050 | F16: =F14*F15 -> 486202.5 | G16: =G14*G15 -> 510512.62 | H16: =H14*H15 -> 536038.26
B18: Count | C18: =C6+C10+C14 -> 6 | D18: =D6+D10+D14 -> 6 | E18: =E6+E10+E14 -> 6 | F18: =F6+F10+F14 -> 6 | G18: =G6+G10+G14 -> 6 | H18: =H6+H10+H14 -> 6
B19: Compensation | C19: =C8+C12+C16 -> 1650000 | D19: =D8+D12+D16 -> 1732500 | E19: =E8+E12+E16 -> 1819125 | F19: =F8+F12+F16 -> 1910081.3 | G19: =G8+G12+G16 -> 2005585.3 | H19: =H8+H12+H16 -> 2105864.6
B21: Headcount increase (YoY) | C21: =C18 -> 6 | D21: =D18-C18 -> 0 | E21: =E18-D18 -> 0 | F21: =F18-E18 -> 0 | G21: =G18-F18 -> 0 | H21: =H18-G18 -> 0
B22: Avg yearly wage | C22: =(C7+C11+C15)/(C6+C10+C14) -> 170000 | D22: =(D7+D11+D15)/(D6+D10+D14) -> 178500 | E22: =(E7+E11+E15)/(E6+E10+E14) -> 187425 | F22: =(F7+F11+F15)/(F6+F10+F14) -> 196796.25 | G22: =(G7+G11+G15)/(G6+G10+G14) -> 206636.06 | H22: =(H7+H11+H15)/(H6+H10+H14) -> 216967.87
C25: =start_year -> 2024 | D25: =C25+1 -> 2025 | E25: =D25+1 -> 2026 | F25: =E25+1 -> 2027 | G25: =F25+1 -> 2028 | H25: =G25+1 -> 2029
B26: S & M
B27: =Input!B40 -> S & M staff
B28: Count | C28: =Input!C40 -> 2 | D28: =Input!D40 -> 3 | E28: =Input!E40 -> 3 | F28: =Input!F40 -> 3 | G28: =Input!G40 -> 3 | H28: =Input!H40 -> 3
B29: Compensation | C29: =Input!$E$53*(1+Input!$C$93)^(C$3-start_year) -> 210000 | D29: =Input!$E$53*(1+Input!$C$93)^(D$3-start_year) -> 220500 | E29: =Input!$E$53*(1+Input!$C$93)^(E$3-start_year) -> 231525 | F29: =Input!$E$53*(1+Input!$C$93)^(F$3-start_year) -> 243101.25 | G29: =Input!$E$53*(1+Input!$C$93)^(G$3-start_year) -> 255256.31 | H29: =Input!$E$53*(1+Input!$C$93)^(H$3-start_year) -> 268019.13
B30: Total Compensation | C30: =C28*C29 -> 420000 | D30: =D28*D29 -> 661500 | E30: =E28*E29 -> 694575 | F30: =F28*F29 -> 729303.75 | G30: =G28*G29 -> 765768.94 | H30: =H28*H29 -> 804057.38
B32: Count | C32: =C28 -> 2 | D32: =D28 -> 3 | E32: =E28 -> 3 | F32: =F28 -> 3 | G32: =G28 -> 3 | H32: =H28 -> 3
B33: Compensation | C33: =C30 -> 420000 | D33: =D30 -> 661500 | E33: =E30 -> 694575 | F33: =F30 -> 729303.75 | G33: =G30 -> 765768.94 | H33: =H30 -> 804057.38
B35: Headcount increase (YoY) | C35: =C32 -> 2 | D35: =D32 -> 3 | E35: =E32 -> 3 | F35: =F32 -> 3 | G35: =G32 -> 3 | H35: =H32 -> 3
B36: Avg yearly wage | C36: =(C30)/(C28) -> 210000 | D36: =(D30)/(D28) -> 220500 | E36: =(E30)/(E28) -> 231525 | F36: =(F30)/(F28) -> 243101.25 | G36: =(G30)/(G28) -> 255256.31 | H36: =(H30)/(H28) -> 268019.13
C39: =start_year -> 2024 | D39: =C39+1 -> 2025 | E39: =D39+1 -> 2026 | F39: =E39+1 -> 2027 | G39: =F39+1 -> 2028 | H39: =G39+1 -> 2029
B40: Direct labor
B41: =Input!B42 -> Editor in Chief
B42: Count | C42: =Input!C42 -> 2 | D42: =Input!D42 -> 2 | E42: =Input!E42 -> 2 | F42: =Input!F42 -> 2 | G42: =Input!G42 -> 2 | H42: =Input!H42 -> 2
B43: Compensation | C43: =Input!$E$55*(1+Input!$C$93)^(C$39-start_year) -> 0 | D43: =Input!$E$55*(1+Input!$C$93)^(D$39-start_year) -> 0 | E43: =Input!$E$55*(1+Input!$C$93)^(E$39-start_year) -> 0 | F43: =Input!$E$55*(1+Input!$C$93)^(F$39-start_year) -> 0 | G43: =Input!$E$55*(1+Input!$C$93)^(G$39-start_year) -> 0 | H43: =Input!$E$55*(1+Input!$C$93)^(H$39-start_year) -> 0
B44: Total Compensation | C44: =C42*C43 -> 0 | D44: =D42*D43 -> 0 | E44: =E42*E43 -> 0 | F44: =F42*F43 -> 0 | G44: =G42*G43 -> 0 | H44: =H42*H43 -> 0
B45: =Input!B43 -> Coordinator
B46: Count | C46: =Input!C43 -> 2 | D46: =Input!D43 -> 2 | E46: =Input!E43 -> 2 | F46: =Input!F43 -> 2 | G46: =Input!G43 -> 2 | H46: =Input!H43 -> 2
B47: Compensation | C47: =Input!$E$56*(1+Input!$C$93)^(C$39-start_year) -> 210000 | D47: =Input!$E$56*(1+Input!$C$93)^(D$39-start_year) -> 220500 | E47: =Input!$E$56*(1+Input!$C$93)^(E$39-start_year) -> 231525 | F47: =Input!$E$56*(1+Input!$C$93)^(F$39-start_year) -> 243101.25 | G47: =Input!$E$56*(1+Input!$C$93)^(G$39-start_year) -> 255256.31 | H47: =Input!$E$56*(1+Input!$C$93)^(H$39-start_year) -> 268019.13
B48: Total Compensation | C48: =C46*C47 -> 420000 | D48: =D46*D47 -> 441000 | E48: =E46*E47 -> 463050 | F48: =F46*F47 -> 486202.5 | G48: =G46*G47 -> 510512.62 | H48: =H46*H47 -> 536038.26
B49: =Input!B44 -> Language Editor
B50: Count | C50: =Input!C44 -> 2 | D50: =Input!D44 -> 2 | E50: =Input!E44 -> 2 | F50: =Input!F44 -> 2 | G50: =Input!G44 -> 2 | H50: =Input!H44 -> 2
B51: Compensation | C51: =Input!$E$57*(1+Input!$C$93)^(C$39-start_year) -> 336000 | D51: =Input!$E$57*(1+Input!$C$93)^(D$39-start_year) -> 352800 | E51: =Input!$E$57*(1+Input!$C$93)^(E$39-start_year) -> 370440 | F51: =Input!$E$57*(1+Input!$C$93)^(F$39-start_year) -> 388962 | G51: =Input!$E$57*(1+Input!$C$93)^(G$39-start_year) -> 408410.1 | H51: =Input!$E$57*(1+Input!$C$93)^(H$39-start_year) -> 428830.61
B52: Total Compensation | C52: =C50*C51 -> 672000 | D52: =D50*D51 -> 705600 | E52: =E50*E51 -> 740880 | F52: =F50*F51 -> 777924 | G52: =G50*G51 -> 816820.2 | H52: =H50*H51 -> 857661.21
B54: Count | C54: =C42+C46+C50 -> 6 | D54: =D42+D46+D50 -> 6 | E54: =E42+E46+E50 -> 6 | F54: =F42+F46+F50 -> 6 | G54: =G42+G46+G50 -> 6 | H54: =H42+H46+H50 -> 6
B55: Compensation | C55: =C44+C48+C52 -> 1092000 | D55: =D44+D48+D52 -> 1146600 | E55: =E44+E48+E52 -> 1203930 | F55: =F44+F48+F52 -> 1264126.5 | G55: =G44+G48+G52 -> 1327332.8 | H55: =H44+H48+H52 -> 1393699.5
B57: Headcount increase (YoY) | C57: =C54 -> 6 | D57: =D54 -> 6 | E57: =E54 -> 6 | F57: =F54 -> 6 | G57: =G54 -> 6 | H57: =H54 -> 6
B58: Avg yearly wage | C58: =(C44+C48+C52)/(C42+C46+C50) -> 182000 | D58: =(D44+D48+D52)/(D42+D46+D50) -> 191100 | E58: =(E44+E48+E52)/(E42+E46+E50) -> 200655 | F58: =(F44+F48+F52)/(F42+F46+F50) -> 210687.75 | G58: =(G44+G48+G52)/(G42+G46+G50) -> 221222.14 | H58: =(H44+H48+H52)/(H42+H46+H50) -> 232283.24
B61: Total Count | C61: =C18+C32+C54 -> 14 | D61: =D18+D32+D54 -> 15 | E61: =E18+E32+E54 -> 15 | F61: =F18+F32+F54 -> 15 | G61: =G18+G32+G54 -> 15 | H61: =H18+H32+H54 -> 15
B62: Total Compensation | C62: =C19+C33+C55 -> 3162000 | D62: =D19+D33+D55 -> 3540600 | E62: =E19+E33+E55 -> 3717630 | F62: =F19+F33+F55 -> 3903511.5 | G62: =G19+G33+G55 -> 4098687.1 | H62: =H19+H33+H55 -> 4303621.4

Sheet Costs
B1: Opex
C6: =start_year -> 2024 | D6: =C6+1 -> 2025 | E6: =D6+1 -> 2026 | F6: =E6+1 -> 2027 | G6: =F6+1 -> 2028 | H6: =G6+1 -> 2029
B7: G&A (Non operating costs)
B8: G&A Labor | C8: =Manpower!C19 -> 1650000 | D8: =Manpower!D19 -> 1732500 | E8: =Manpower!E19 -> 1819125 | F8: =Manpower!F19 -> 1910081.3 | G8: =Manpower!G19 -> 2005585.3 | H8: =Manpower!H19 -> 2105864.6
B9: Hiring Costs | C9: =Input!$C$63 -> 140000 | D9: =Input!$C$63 -> 140000 | E9: =Input!$C$63 -> 140000 | F9: =Input!$C$63 -> 140000 | G9: =Input!$C$63 -> 140000 | H9: =Input!$C$63 -> 140000
B10: Total G&A | C10: =SUM(C8:C9) -> 1790000 | D10: =SUM(D8:D9) -> 1872500 | E10: =SUM(E8:E9) -> 1959125 | F10: =SUM(F8:F9) -> 2050081.3 | G10: =SUM(G8:G9) -> 2145585.3 | H10: =SUM(H8:H9) -> 2245864.6
B12: S&M (Non operating costs)
B13: S&M Labor | C13: =Manpower!C33 -> 420000 | D13: =Manpower!D33 -> 661500 | E13: =Manpower!E33 -> 694575 | F13: =Manpower!F33 -> 729303.75 | G13: =Manpower!G33 -> 765768.94 | H13: =Manpower!H33 -> 804057.38
B14: Supplies | C14: =(Input!$C$65)*(1+Input!$C$99)^(C6-start_year) -> 375000 | D14: =(Input!$C$65)*(1+Input!$C$99)^(D6-start_year) -> 393750 | E14: =(Input!$C$65)*(1+Input!$C$99)^(E6-start_year) -> 413437.5 | F14: =(Input!$C$65)*(1+Input!$C$99)^(F6-start_year) -> 434109.38 | G14: =(Input!$C$65)*(1+Input!$C$99)^(G6-start_year) -> 455814.84 | H14: =(Input!$C$65)*(1+Input!$C$99)^(H6-start_year) -> 478605.59
B15: Advertising | C15: =(Input!$C$66)*(1+Input!$C$99)^(C6-start_year) -> 752000 | D15: =(Input!$C$66)*(1+Input!$C$99)^(D6-start_year) -> 789600 | E15: =(Input!$C$66)*(1+Input!$C$99)^(E6-start_year) -> 829080 | F15: =(Input!$C$66)*(1+Input!$C$99)^(F6-start_year) -> 870534 | G15: =(Input!$C$66)*(1+Input!$C$99)^(G6-start_year) -> 914060.7 | H15: =(Input!$C$66)*(1+Input!$C$99)^(H6-start_year) -> 959763.74
B16: Travel | C16: =(Input!$C$67)*(1+Input!$C$99)^(C6-start_year) -> 330000 | D16: =(Input!$C$67)*(1+Input!$C$99)^(D6-start_year) -> 346500 | E16: =(Input!$C$67)*(1+Input!$C$99)^(E6-start_year) -> 363825 | F16: =(Input!$C$67)*(1+Input!$C$99)^(F6-start_year) -> 382016.25 | G16: =(Input!$C$67)*(1+Input!$C$99)^(G6-start_year) -> 401117.06 | H16: =(Input!$C$67)*(1+Input!$C$99)^(H6-start_year) -> 421172.92
B17: Commissions | C17: =Input!$D$68*Revenues!C8 -> 0 | D17: =Input!$D$68*Revenues!D8 -> 0 | E17: =Input!$D$68*Revenues!E8 -> 0 | F17: =Input!$D$68*Revenues!F8 -> 0 | G17: =Input!$D$68*Revenues!G8 -> 0 | H17: =Input!$D$68*Revenues!H8 -> 0
B18: Total S&M | C18: =SUM(C13:C17) -> 1877000 | D18: =SUM(D13:D17) -> 2191350 | E18: =SUM(E13:E17) -> 2300917.5 | F18: =SUM(F13:F17) -> 2415963.4 | G18: =SUM(G13:G17) -> 2536761.5 | H18: =SUM(H13:H17) -> 2663599.6
B20: COGS (Operating costs)
B21: Subscription cost | C21: =Input!C19*Input!C23 -> 940000 | D21: =Input!D19*Input!D23 -> 1113430 | E21: =Input!E19*Input!E23 -> 1318857.8 | F21: =Input!F19*Input!F23 -> 1562187.1 | G21: =Input!G19*Input!G23 -> 1850410.6 | H21: =Input!H19*Input!H23 -> 2191811.4
B22: Direct Labor | C22: =Manpower!C55 -> 1092000 | D22: =Manpower!D55 -> 1146600 | E22: =Manpower!E55 -> 1203930 | F22: =Manpower!F55 -> 1264126.5 | G22: =Manpower!G55 -> 1327332.8 | H22: =Manpower!H55 -> 1393699.5
B23: Other COGS
B24: Total COGS | C24: =SUM(C21:C23) -> 2032000 | D24: =SUM(D21:D23) -> 2260030 | E24: =SUM(E21:E23) -> 2522787.8 | F24: =SUM(F21:F23) -> 2826313.6 | G24: =SUM(G21:G23) -> 3177743.5 | H24: =SUM(H21:H23) -> 3585510.9
B26: Total Costs | C26: =C10+C18+C24 -> 5699000 | D26: =D10+D18+D24 -> 6323880 | E26: =E10+E18+E24 -> 6782830.3 | F26: =F10+F18+F24 -> 7292358.2 | G26: =G10+G18+G24 -> 7860090.3 | H26: =H10+H18+H24 -> 8494975.1 | I26: =SUM(C26:H26) -> 42453134

Sheet Capex & Dep
B1: Capex & Depreciation
C5: =start_year-1 -> 2023 | D5: =start_year -> 2024 | E5: =D5+1 -> 2025 | F5: =E5+1 -> 2026 | G5: =F5+1 -> 2027 | H5: =G5+1 -> 2028 | I5: =H5+1 -> 2029
B6: Assets
B7: Net addition to gross assets | C7: =Input!C76 -> 937500 | D7: =Input!D76 -> 0 | E7: =Input!E76 -> 0 | F7: =Input!F76 -> 0 | G7: =Input!G76 -> 0 | H7: =Input!H76 -> 0 | I7: =Input!I76 -> 0
B8: Gross Assets | C8: =SUM(C7:$C7) -> 937500 | D8: =SUM($C7:D7) -> 937500 | E8: =SUM($C7:E7) -> 937500 | F8: =SUM($C7:F7) -> 937500 | G8: =SUM($C7:G7) -> 937500 | H8: =SUM($C7:H7) -> 937500 | I8: =SUM($C7:I7) -> 937500
B10: Beginning of Yr Undepreciated Assets | C10: =C8 -> 937500 | D10: =C13+D7 -> 937500 | E10: =D13+E7 -> 843750 | F10: =E13+F7 -> 750000 | G10: =F13+G7 -> 656250 | H10: =G13+H7 -> 562500 | I10: =H13+I7 -> 468750
D11: 0 | E11: 0 | F11: 0 | G11: 0 | H11: 0 | I11: 0
B12: Depreciation | C12: 0 | D12: =D10/Input!$C$94 -> 93750 | E12: =($D$10/Input!$C$94)+(E7/Input!$C$94) -> 93750 | F12: =($D$10/Input!$C$94)+(E7/Input!$C$94)+(F7/Input!$C$94) -> 93750 | G12: =($D$10/Input!$C$94)+(E7/Input!$C$94)+(F7/Input!$C$94)+(G7/Input!$C$94) -> 93750 | H12: =($D$10/Input!$C$94)+(E7/Input!$C$94)+(F7/Input!$C$94)+(G7/Input!$C$94)+(H7/Input!$C$94) -> 93750 | I12: =($D$10/Input!$C$94)+(E7/Input!$C$94)+(F7/Input!$C$94)+(G7/Input!$C$94)+(H7/Input!$C$94)+(I7/Input!$C$94) -> 93750
B13: End of Yr Undepreciated Assets | C13: =C10-C12 -> 937500 | D13: =D10-D12 -> 843750 | E13: =E10-E12 -> 750000 | F13: =F10-F12 -> 656250 | G13: =G10-G12 -> 562500 | H13: =H10-H12 -> 468750 | I13: =I10-I12 -> 375000

Sheet Working Capital
B1: Working Capital
C4: =start_year -> 2024 | D4: =C4+1 -> 2025 | E4: =D4+1 -> 2026 | F4: =E4+1 -> 2027 | G4: =F4+1 -> 2028 | H4: =G4+1 -> 2029
B5: Accounts payable G&A | C5: =(Costs!C10-Costs!C8)*Input!C28/day_in_year -> 11666.667 | D5: =(Costs!D10-Costs!D8)*Input!D28/day_in_year -> 11666.667 | E5: =(Costs!E10-Costs!E8)*Input!E28/day_in_year -> 11666.667 | F5: =(Costs!F10-Costs!F8)*Input!F28/day_in_year -> 11666.667 | G5: =(Costs!G10-Costs!G8)*Input!G28/day_in_year -> 11666.667 | H5: =(Costs!H10-Costs!H8)*Input!H28/day_in_year -> 11666.667
B6: Accounts payable S&M | C6: =(Costs!C18-Costs!C13)*Input!C29/day_in_year -> 121416.67 | D6: =(Costs!D18-Costs!D13)*Input!D29/day_in_year -> 127487.5 | E6: =(Costs!E18-Costs!E13)*Input!E29/day_in_year -> 133861.88 | F6: =(Costs!F18-Costs!F13)*Input!F29/day_in_year -> 140554.97 | G6: =(Costs!G18-Costs!G13)*Input!G29/day_in_year -> 147582.72 | H6: =(Costs!H18-Costs!H13)*Input!H29/day_in_year -> 154961.85
B7: Accounts payable COGS | C7: =(Costs!C24-Costs!C22)*Input!C30/day_in_year -> 78333.333 | D7: =(Costs!D24-Costs!D22)*Input!D30/day_in_year -> 92785.833 | E7: =(Costs!E24-Costs!E22)*Input!E30/day_in_year -> 109904.82 | F7: =(Costs!F24-Costs!F22)*Input!F30/day_in_year -> 130182.26 | G7: =(Costs!G24-Costs!G22)*Input!G30/day_in_year -> 154200.89 | H7: =(Costs!H24-Costs!H22)*Input!H30/day_in_year -> 182650.95
B8: Total accounts payable | C8: =SUM(C5:C7) -> 211416.67 | D8: =SUM(D5:D7) -> 231940 | E8: =SUM(E5:E7) -> 255433.36 | F8: =SUM(F5:F7) -> 282403.89 | G8: =SUM(G5:G7) -> 313450.27 | H8: =SUM(H5:H7) -> 349279.47
B9: Total inventory | C9: =Costs!C24*Input!C32/day_in_year -> 169333.33 | D9: =Costs!D24*Input!D32/day_in_year -> 188335.83 | E9: =Costs!E24*Input!E32/day_in_year -> 210232.32 | F9: =Costs!F24*Input!F32/day_in_year -> 235526.13 | G9: =Costs!G24*Input!G32/day_in_year -> 264811.95 | H9: =Costs!H24*Input!H32/day_in_year -> 298792.57
B10: Total accounts receivable | C10: =Revenues!C8*Input!C31/day_in_year -> 1562500 | D10: =Revenues!D8*Input!D31/day_in_year -> 1850781.2 | E10: =Revenues!E8*Input!E31/day_in_year -> 2192250.4 | F10: =Revenues!F8*Input!F31/day_in_year -> 2596720.6 | G10: =Revenues!G8*Input!G31/day_in_year -> 3075815.5 | H10: =Revenues!H8*Input!H31/day_in_year -> 3643303.5
B12: Working Capital | C12: =C10-C8+C9 -> 1520416.7 | D12: =D10-D8+D9 -> 1807177.1 | E12: =E10-E8+E9 -> 2147049.3 | F12: =F10-F8+F9 -> 2549842.8 | G12: =G10-G8+G9 -> 3027177.2 | H12: =H10-H8+H9 -> 3592816.6
B13: Change in Working Capital | C13: =C12 -> 1520416.7 | D13: =D12-C12 -> 286760.42 | E13: =E12-D12 -> 339872.27 | F13: =F12-E12 -> 402793.48 | G13: =G12-F12 -> 477334.39 | H13: =H12-G12 -> 565639.38
B15: Working Capital (% Revenues) | D15: =D12/Revenues!D8 -> 0.32548004 | E15: =E12/Revenues!E8 -> 0.32646048 | F15: =F12/Revenues!F8 -> 0.32731577 | G15: =G12/Revenues!G8 -> 0.32806229 | H15: =H12/Revenues!H8 -> 0.32871418

Sheet Financial Statements
B1: Financial Statements
B4: Income Statement (SAR)
C5: Yr 0 | D5: =start_year -> 2024 | E5: =D5+1 -> 2025 | F5: =E5+1 -> 2026 | G5: =F5+1 -> 2027 | H5: =G5+1 -> 2028 | I5: =H5+1 -> 2029
B6: Sales revenues
B7: Sales revenues | D7: =Revenues!C8 -> 4687500 | E7: =Revenues!D8 -> 5552343.7 | F7: =Revenues!E8 -> 6576751.2 | G7: =Revenues!F8 -> 7790161.8 | H7: =Revenues!G8 -> 9227446.6 | I7: =Revenues!H8 -> 10929911
B8: Net sales revenues | D8: =SUM(D7) -> 4687500 | E8: =SUM(E7) -> 5552343.7 | F8: =SUM(F7) -> 6576751.2 | G8: =SUM(G7) -> 7790161.8 | H8: =SUM(H7) -> 9227446.6 | I8: =SUM(I7) -> 10929911
B10: COGS | D10: =Costs!C24 -> 2032000 | E10: =Costs!D24 -> 2260030 | F10: =Costs!E24 -> 2522787.8 | G10: =Costs!F24 -> 2826313.6 | H10: =Costs!G24 -> 3177743.5 | I10: =Costs!H24 -> 3585510.9
B12: Gross Profit | D12: =D8-D10 -> 2655500 | E12: =E8-E10 -> 3292313.7 | F12: =F8-F10 -> 4053963.3 | G12: =G8-G10 -> 4963848.2 | H12: =H8-H10 -> 6049703.2 | I12: =I8-I10 -> 7344399.7
B13: Gross margin | D13: =D12/D8 -> 0.56650667 | E13: =E12/E8 -> 0.59295928 | F13: =F12/F8 -> 0.6164082 | G13: =G12/G8 -> 0.63719449 | H13: =H12/H8 -> 0.6556205 | I13: =I12/I8 -> 0.67195424
B15: G&A & S&M
B16: G&A | D16: =Costs!C10 -> 1790000 | E16: =Costs!D10 -> 1872500 | F16: =Costs!E10 -> 1959125 | G16: =Costs!F10 -> 2050081.3 | H16: =Costs!G10 -> 2145585.3 | I16: =Costs!H10 -> 2245864.6
B17: S&M | D17: =Costs!C18 -> 1877000 | E17: =Costs!D18 -> 2191350 | F17: =Costs!E18 -> 2300917.5 | G17: =Costs!F18 -> 2415963.4 | H17: =Costs!G18 -> 2536761.5 | I17: =Costs!H18 -> 2663599.6
B18: Management fee | D18: =(Input!$C$97*D79) -> 0 | E18: =(Input!$C$97*E79) -> 0 | F18: =(Input!$C$97*F79) -> 0 | G18: =(Input!$C$97*G79) -> 0 | H18: =(Input!$C$97*H79) -> 0 | I18: =(Input!$C$97*I79) -> 0
B19: EBITDA | D19: =D12-SUM(D16:D18) -> -1011500 | E19: =E12-SUM(E16:E18) -> -771536.25 | F19: =F12-SUM(F16:F18) -> -206079.16 | G19: =G12-SUM(G16:G18) -> 497803.53 | H19: =H12-SUM(H16:H18) -> 1367356.3 | I19: =I12-SUM(I16:I18) -> 2434935.5
B20: EBITDA margin | D20: =D19/D8 -> -0.21578667 | E20: =E19/E8 -> -0.13895686 | F20: =F19/F8 -> -0.031334493 | G20: =G19/G8 -> 0.063901566 | H20: =H19/H8 -> 0.1481836 | I20: =I19/I8 -> 0.22277725
B21: Depreciation
B22: Fixed assets depreciation | D22: ='Capex & Dep'!D12 -> 93750 | E22: ='Capex & Dep'!E12 -> 93750 | F22: ='Capex & Dep'!F12 -> 93750 | G22: ='Capex & Dep'!G12 -> 93750 | H22: ='Capex & Dep'!H12 -> 93750 | I22: ='Capex & Dep'!I12 -> 93750
B23: Total depreciation expenses | D23: =D22 -> 93750 | E23: =E22 -> 93750 | F23: =F22 -> 93750 | G23: =G22 -> 93750 | H23: =H22 -> 93750 | I23: =I22 -> 93750
B25: EBIT | D25: =D19-D23 -> -1105250 | E25: =E19-E23 -> -865286.25 | F25: =F19-F23 -> -299829.16 | G25: =G19-G23 -> 404053.53 | H25: =H19-H23 -> 1273606.3 | I25: =I19-I23 -> 2341185.5
B26: EBIT margin | D26: =D25/D7 -> -0.23578667 | E26: =E25/E7 -> -0.15584162 | F26: =F25/F7 -> -0.045589251 | G26: =G25/G7 -> 0.051867156 | H26: =H25/H7 -> 0.1380237 | I26: =I25/I7 -> 0.21419987
B28: Zakah | D28: =D99 -> 0 | E28: =E99 -> 59486.594 | F28: =F99 -> 84097.45 | G28: =G99 -> 113190.1 | H28: =H99 -> 144544.26 | I28: =I99 -> 201804.04
B29: Dividends | D29: 0 | E29: 0 | F29: 0 | G29: 0 | H29: 0 | I29: 0
B31: Net income | D31: =D25-D28-D29 -> -1105250 | E31: =E25-E28-E29 -> -924772.84 | F31: =F25-F28-F29 -> -383926.61 | G31: =G25-G28-G29 -> 290863.43 | H31: =H25-H28-H29 -> 1129062 | I31: =I25-I28-I29 -> 2139381.4
B32: Net margin | D32: =D31/D8 -> -0.23578667 | E32: =E31/E8 -> -0.1665554 | F32: =F31/F8 -> -0.058376332 | G32: =G31/G8 -> 0.037337277 | H32: =H31/H8 -> 0.1223591 | I32: =I31/I8 -> 0.19573641
B36: Cash flow statement (SAR)
C37: Yr 0 | D37: =start_year -> 2024 | E37: =D37+1 -> 2025 | F37: =E37+1 -> 2026 | G37: =F37+1 -> 2027 | H37: =G37+1 -> 2028 | I37: =H37+1 -> 2029
B38: Cash Flow from operations
B39: Net income | C39: 0 | D39: =D31 -> -1105250 | E39: =E31 -> -924772.84 | F39: =F31 -> -383926.61 | G39: =G31 -> 290863.43 | H39: =H31 -> 1129062 | I39: =I31 -> 2139381.4
B40: Depreciation | C40: 0 | D40: =D22 -> 93750 | E40: =E22 -> 93750 | F40: =F22 -> 93750 | G40: =G22 -> 93750 | H40: =H22 -> 93750 | I40: =I22 -> 93750
B41: Change in Net Working Capital | C41: 0 | D41: ='Working Capital'!C13 -> 1520416.7 | E41: ='Working Capital'!D13 -> 286760.42 | F41: ='Working Capital'!E13 -> 339872.27 | G41: ='Working Capital'!F13 -> 402793.48 | H41: ='Working Capital'!G13 -> 477334.39 | I41: ='Working Capital'!H13 -> 565639.38
B42: Total cash flow from operations | C42: =C39+C40-C41 -> 0 | D42: =D39+D40-D41 -> -2531916.7 | E42: =E39+E40-E41 -> -1117783.3 | F42: =F39+F40-F41 -> -630048.88 | G42: =G39+G40-G41 -> -18180.048 | H42: =H39+H40-H41 -> 745477.65 | I42: =I39+I40-I41 -> 1667492
B44: Cash Flow from investing
B45: Capex/maintenance capex | C45: ='Capex & Dep'!C7 -> 937500 | D45: ='Capex & Dep'!D7 -> 0 | E45: ='Capex & Dep'!E7 -> 0 | F45: ='Capex & Dep'!F7 -> 0 | G45: ='Capex & Dep'!G7 -> 0 | H45: ='Capex & Dep'!H7 -> 0 | I45: ='Capex & Dep'!I7 -> 0
B46: Total cash flow from investment | C46: =-C45 -> -937500 | D46: =-D45 -> 0 | E46: =-E45 -> 0 | F46: =-F45 -> 0 | G46: =-G45 -> 0 | H46: =-H45 -> 0 | I46: =-I45 -> 0
B50: Total cash from from financing
B51: =Input!B86 -> Hevolution | C51: =Input!C86 -> 2550000 | D51: =Input!D86 -> 2550000 | E51: =Input!E86 -> 1250000 | F51: =Input!F86 -> 750000 | G51: =Input!G86 -> 0 | H51: =Input!H86 -> 0 | I51: =Input!I86 -> 0
B52: =Input!B87 -> Other Parties | C52: =Input!C87 -> 0 | D52: =Input!D87 -> 0 | E52: =Input!E87 -> 0 | F52: =Input!F87 -> 0 | G52: =Input!G87 -> 0 | H52: =Input!H87 -> 0 | I52: =Input!I87 -> 0
B53: Loan repayment | C53: 0 | D53: =IF(Input!$C$95=0,Input!$C$87/Input!$C$96,0) -> 0 | E53: =IF(Input!$C$95>1,0,Input!$C$87/Input!$C$96) -> 0 | F53: =IF(Input!$C$95>2,0,Input!$C$87/Input!$C$96) -> 0 | G53: =IF(Input!$C$95>3,0,Input!$C$87/Input!$C$96) -> 0 | H53: =IF(Input!$C$95>4,0,Input!$C$87/Input!$C$96) -> 0 | I53: =IF(Input!$C$95=0,0,Input!$C$87/Input!$C$96) -> 0
B54: Total cash flow from financing | C54: =C51+C52-C53 -> 2550000 | D54: =D51+D52-D53 -> 2550000 | E54: =E51+E52-E53 -> 1250000 | F54: =F51+F52-F53 -> 750000 | G54: =G51+G52-G53 -> 0 | H54: =H51+H52-H53 -> 0 | I54: =I51+I52-I53 -> 0
B56: Net cash flow | C56: =C42+C46+C54 -> 1612500 | D56: =D42+D46+D54 -> 18083.333 | E56: =E42+E46+E54 -> 132216.74 | F56: =F42+F46+F54 -> 119951.12 | G56: =G42+G46+G54 -> -18180.048 | H56: =H42+H46+H54 -> 745477.65 | I56: =I42+I46+I54 -> 1667492
B58: Cash position
B59: Beginning balance | C59: 0 | D59: =C60 -> 1612500 | E59: =D60 -> 1630583.3 | F59: =E60 -> 1762800.1 | G59: =F60 -> 1882751.2 | H59: =G60 -> 1864571.1 | I59: =H60 -> 2610048.8
B60: Ending balance | C60: =C56 -> 1612500 | D60: =D59+D56 -> 1630583.3 | E60: =E59+E56 -> 1762800.1 | F60: =F59+F56 -> 1882751.2 | G60: =G59+G56 -> 1864571.1 | H60: =H59+H56 -> 2610048.8 | I60: =I59+I56 -> 4277540.8
B62: DSCR | D62: =(D42+D18-D45+C60)/(D18+D53) -> #DIV/0! | E62: =(E42+E18-E45)/(E18+E53) -> #DIV/0! | F62: =(F42+F18-F45)/(F18+F53) -> #DIV/0! | G62: =(G42+G18-G45)/(G18+G53) -> #DIV/0! | H62: =(H42+H18-H45)/(H18+H53) -> #DIV/0! | I62: =(I42+I18-I45)/(I18+I53) -> #DIV/0!
B64: Balance Sheet (SAR)
C65: Yr 0 | D65: =start_year -> 2024 | E65: =D65+1 -> 2025 | F65: =E65+1 -> 2026 | G65: =F65+1 -> 2027 | H65: =G65+1 -> 2028 | I65: =H65+1 -> 2029
B66: Assets
B67: Fixed Assets | C67: ='Capex & Dep'!C13 -> 937500 | D67: ='Capex & Dep'!D13 -> 843750 | E67: ='Capex & Dep'!E13 -> 750000 | F67: ='Capex & Dep'!F13 -> 656250 | G67: ='Capex & Dep'!G13 -> 562500 | H67: ='Capex & Dep'!H13 -> 468750 | I67: ='Capex & Dep'!I13 -> 375000
B68: Current assets | C68: =SUM(C69:C72) -> 1612500 | D68: =SUM(D69:D72) -> 3362416.7 | E68: =SUM(E69:E72) -> 3801917.2 | F68: =SUM(F69:F72) -> 4285233.9 | G68: =SUM(G69:G72) -> 4696817.9 | H68: =SUM(H69:H72) -> 5950676.3 | I68: =SUM(I69:I72) -> 8219636.9
B69: Cash | C69: =MAX(0,+C60) -> 1612500 | D69: =MAX(0,+D60) -> 1630583.3 | E69: =MAX(0,+E60) -> 1762800.1 | F69: =MAX(0,+F60) -> 1882751.2 | G69: =MAX(0,+G60) -> 1864571.1 | H69: =MAX(0,+H60) -> 2610048.8 | I69: =MAX(0,+I60) -> 4277540.8
B70: Receivables | C70: 0 | D70: ='Working Capital'!C10 -> 1562500 | E70: ='Working Capital'!D10 -> 1850781.2 | F70: ='Working Capital'!E10 -> 2192250.4 | G70: ='Working Capital'!F10 -> 2596720.6 | H70: ='Working Capital'!G10 -> 3075815.5 | I70: ='Working Capital'!H10 -> 3643303.5
B71: Inventory | C71: 0 | D71: ='Working Capital'!C9 -> 169333.33 | E71: ='Working Capital'!D9 -> 188335.83 | F71: ='Working Capital'!E9 -> 210232.32 | G71: ='Working Capital'!F9 -> 235526.13 | H71: ='Working Capital'!G9 -> 264811.95 | I71: ='Working Capital'!H9 -> 298792.57
B72: Other
B73: Liabilities
B74: Current liabilities | C74: =SUM(C75:C77) -> 0 | D74: =SUM(D75:D77) -> 211416.67 | E74: =SUM(E75:E77) -> 231940 | F74: =SUM(F75:F77) -> 255433.36 | G74: =SUM(G75:G77) -> 282403.89 | H74: =SUM(H75:H77) -> 313450.27 | I74: =SUM(I75:I77) -> 349279.47
B75: Overdraft | C75: =0-MIN(0,+C60) -> 0 | D75: =0-MIN(0,+D60) -> 0 | E75: =0-MIN(0,+E60) -> 0 | F75: =0-MIN(0,+F60) -> 0 | G75: =0-MIN(0,+G60) -> 0 | H75: =0-MIN(0,+H60) -> 0 | I75: =0-MIN(0,+I60) -> 0
B76: Payables | C76: 0 | D76: ='Working Capital'!C8 -> 211416.67 | E76: ='Working Capital'!D8 -> 231940 | F76: ='Working Capital'!E8 -> 255433.36 | G76: ='Working Capital'!F8 -> 282403.89 | H76: ='Working Capital'!G8 -> 313450.27 | I76: ='Working Capital'!H8 -> 349279.47
B77: Other
B78: Long term liabilities | C78: =SUM(C79:C80) -> 0 | D78: =SUM(D79:D80) -> 0 | E78: =SUM(E79:E80) -> 0 | F78: =SUM(F79:F80) -> 0 | G78: =SUM(G79:G80) -> 0 | H78: =SUM(H79:H80) -> 0 | I78: =SUM(I79:I80) -> 0
B79: Senior debt | C79: =Input!C87 -> 0 | D79: =Input!D87-D53+C79 -> 0 | E79: =Input!E87-E53+D79 -> 0 | F79: =Input!F87-F53+E79 -> 0 | G79: =Input!G87-G53+F79 -> 0 | H79: =Input!H87-H53+G79 -> 0 | I79: =Input!I87-I53+H79 -> 0
B80: Subordinated debt
B81: Equity | C81: =SUM(C82:C83) -> 2550000 | D81: =SUM(D82:D83) -> 3994750 | E81: =SUM(E82:E83) -> 4319977.2 | F81: =SUM(F82:F83) -> 4686050.5 | G81: =SUM(G82:G83) -> 4976914 | H81: =SUM(H82:H83) -> 6105976 | I81: =SUM(I82:I83) -> 8245357.4
B82: Shareholders' contribution | C82: =C51 -> 2550000 | D82: =D51+C82 -> 5100000 | E82: =D82+E51 -> 6350000 | F82: =E82+F51 -> 7100000 | G82: =F82+G51 -> 7100000 | H82: =G82+H51 -> 7100000 | I82: =H82+I51 -> 7100000
B83: Retained earnings | C83: =C31 -> 0 | D83: =D31 -> -1105250 | E83: =D83+E31 -> -2030022.8 | F83: =E83+F31 -> -2413949.5 | G83: =F83+G31 -> -2123086 | H83: =G83+H31 -> -994023.98 | I83: =H83+I31 -> 1145357.4
B86: Balance sheet check | C86: =C67+C68-C74-C78-C81 -> 0 | D86: =D67+D68-D74-D78-D81 -> 0 | E86: =E67+E68-E74-E78-E81 -> 0 | F86: =F67+F68-F74-F78-F81 -> 0 | G86: =G67+G68-G74-G78-G81 -> 0 | H86: =H67+H68-H74-H78-H81 -> 0 | I86: =I67+I68-I74-I78-I81 -> 0
B87: Profit and loss check | C87: =C83-0-C31 -> 0 | D87: =D83-0-D31 -> 0 | E87: =E83-D83-E31 -> 0 | F87: =F83-E83-F31 -> 0 | G87: =G83-F83-G31 -> 0 | H87: =H83-G83-H31 -> 0 | I87: =I83-H83-I31 -> 0
B88: Cash flow check | C88: =C69-A69-C75+A75-C60+A60 -> 0 | D88: =D69-C69-D75+C75-D60+C60 -> 0 | E88: =E69-D69-E75+D75-E60+D60 -> 0 | F88: =F69-E69-F75+E75-F60+E60 -> 0 | G88: =G69-F69-G75+F75-G60+F60 -> 0 | H88: =H69-G69-H75+G75-H60+G60 -> 0 | I88: =I69-H69-I75+H75-I60+H60 -> 0
B92: Zakat | C92: Yr 0 | D92: =D65 -> 2024 | E92: =E65 -> 2025 | F92: =F65 -> 2026 | G92: =G65 -> 2027 | H92: =H65 -> 2028 | I92: =I65 -> 2029
B93: Beginning Balance of Equity | C93: 0 | D93: 0 | E93: =D81 -> 3994750 | F93: =E81 -> 4319977.2 | G93: =F81 -> 4686050.5 | H93: =G81 -> 4976914 | I93: =H81 -> 6105976
B94: Loans used to fund the construction of the project | C94: 0 | D94: 0 | E94: =E78 -> 0 | F94: =F78 -> 0 | G94: =G78 -> 0 | H94: =H78 -> 0 | I94: =I78 -> 0
B95: EBIT | C95: 0 | D95: 0 | E95: =E25 -> -865286.25 | F95: =F25 -> -299829.16 | G95: =G25 -> 404053.53 | H95: =H25 -> 1273606.3 | I95: =I25 -> 2341185.5
B96: - Long term investment in other companies | C96: 0 | D96: 0 | E96: 0 | F96: 0 | G96: 0 | H96: 0 | I96: 0
B97: - Fixed Assets | C97: 0 | D97: 0 | E97: =-E67 -> -750000 | F97: =-F67 -> -656250 | G97: =-G67 -> -562500 | H97: =-H67 -> -468750 | I97: =-I67 -> -375000
B98: Zakat Base | C98: =SUM(C93:C97) -> 0 | D98: =SUM(D93:D97) -> 0 | E98: =SUM(E93:E97) -> 2379463.7 | F98: =SUM(F93:F97) -> 3363898 | G98: =SUM(G93:G97) -> 4527604.1 | H98: =SUM(H93:H97) -> 5781770.3 | I98: =SUM(I93:I97) -> 8072161.5
B99: Zakat at 2.5% | C99: =0.025*C98 -> 0 | D99: =0.025*D98 -> 0 | E99: =0.025*E98 -> 59486.594 | F99: =0.025*F98 -> 84097.45 | G99: =0.025*G98 -> 113190.1 | H99: =0.025*H98 -> 144544.26 | I99: =0.025*I98 -> 201804.04
