Workbook

Sheet Executive Dashboard
A1: SAUDI CLINICAL INTELLIGENCE GROUP
A2: Sovereign Clinical Knowledge Infrastructure Platform — Executive Dashboard
A4: COMPANY OVERVIEW | B4: 2026 Revenue | C4: 2031 Revenue | D4: CAGR | E4: EBITDA Margin at Scale | F4: Investment Required | G4: Target Valuation | H4: Status
A5: NAMA Medical | B5: 2500000 | C5: 40000000 | D5: =(C5/B5)^(1/5)-1 | E5: 0.525 | F5: 5000000 | G5: 100000000 | H5: Clinical CRO
A6: Waraqa | B6: 1200000 | C6: 24000000 | D6: =(C6/B6)^(1/5)-1 | E6: 0.45 | F6: 2500000 | G6: 120000000 | H6: Publishing Platform
A7: NAMA Knowledge | B7: 1500000 | C7: 28000000 | D7: =(C7/B7)^(1/5)-1 | E7: 0.34 | F7: 1000000 | G7: 84000000 | H7: MedEd / LMS
A8: NAMA BIO | B8: 2733333 | C8: 15746667 | D8: =(C8/B8)^(1/5)-1 | E8: 0.4 | F8: 4500000 | G8: 50000000 | H8: Bioequivalence Lab
A9: CONSOLIDATED TOTAL | B9: =SUM(B5:B8) | C9: =SUM(C5:C8) | D9: =(C9/B9)^(1/5)-1 | F9: =SUM(F5:F8) | G9: =SUM(G5:G8) | H9: 4 Companies
A11: KEY GROUP METRICS (2026-2031)
A12: Combined Revenue (2026) | B12: ='Consolidated P&L'!B9 | D12: Revenue CAGR (5yr) | E12: =D9
A13: Combined Revenue (2031) | B13: ='Consolidated P&L'!G9 | D13: Revenue per Employee (2030) | E13: ='Consolidated P&L'!F9/'Consolidated P&L'!F37
A14: Peak Revenue (2030) | B14: ='Consolidated P&L'!F9 | D14: Cumulative Revenue (6yr) | E14: =SUM('Consolidated P&L'!B9:G9)
A15: Combined EBITDA (2030) | B15: ='Consolidated P&L'!F29 | D15: Investment MOIC (on Target) | E15: =G9/F9
A16: EBITDA Margin (2030) | B16: ='Consolidated P&L'!F30 | D16: Conservative Valuation | E16: 200000000
A17: Total Investment Required | B17: =F9 | D17: Base Case Valuation | E17: 354000000
A18: Group Valuation (Target) | B18: =G9 | D18: Optimistic Valuation | E18: 500000000
A19: Total Headcount (2030) | B19: ='Consolidated P&L'!F37 | D19: Discount Rate (WACC) | E19: 0.15

Sheet NAMA Medical
A1: NAMA Medical — Detailed P&L
A2: ($, USD) | B2: 2025 | C2: 2026 | D2: 2027 | E2: 2028 | F2: 2029 | G2: 2030 | H2: 2031 | I2: Notes
A3: REVENUE
A4: Total Revenue | B4: 300000 | C4: 2500000 | D4: 5500000 | E4: 10000000 | F4: 18000000 | G4: 30000000 | H4: 40000000
A5: Interventional Trials (39%) | B5: =B$4*0.39 | C5: =C$4*0.39 | D5: =D$4*0.39 | E5: =E$4*0.39 | F5: =F$4*0.39 | G5: =G$4*0.39 | H5: =H$4*0.39
A6: Bioequivalence (19%) | B6: =B$4*0.19 | C6: =C$4*0.19 | D6: =D$4*0.19 | E6: =E$4*0.19 | F6: =F$4*0.19 | G6: =G$4*0.19 | H6: =H$4*0.19
A7: Real-World Evidence (17%) | B7: =B$4*0.17 | C7: =C$4*0.17 | D7: =D$4*0.17 | E7: =E$4*0.17 | F7: =F$4*0.17 | G7: =G$4*0.17 | H7: =H$4*0.17
A8: AI Services (9%) | B8: =B$4*0.09 | C8: =C$4*0.09 | D8: =D$4*0.09 | E8: =E$4*0.09 | F8: =F$4*0.09 | G8: =G$4*0.09 | H8: =H$4*0.09
A9: Medical Writing (7%) | B9: =B$4*0.07 | C9: =C$4*0.07 | D9: =D$4*0.07 | E9: =E$4*0.07 | F9: =F$4*0.07 | G9: =G$4*0.07 | H9: =H$4*0.07
A10: SMO Services (6%) | B10: =B$4*0.06 | C10: =C$4*0.06 | D10: =D$4*0.06 | E10: =E$4*0.06 | F10: =F$4*0.06 | G10: =G$4*0.06 | H10: =H$4*0.06
A11: Publishing (3%) | B11: =B$4*0.03 | C11: =C$4*0.03 | D11: =D$4*0.03 | E11: =E$4*0.03 | F11: =F$4*0.03 | G11: =G$4*0.03 | H11: =H$4*0.03
A13: COST OF REVENUE
A14: COGS % of Revenue | B14: 0.35 | C14: 0.35 | D14: 0.34 | E14: 0.33 | F14: 0.32 | G14: 0.31 | H14: 0.3
A15: Cost of Revenue | B15: =B4*B14 | C15: =C4*C14 | D15: =D4*D14 | E15: =E4*E14 | F15: =F4*F14 | G15: =G4*G14 | H15: =H4*H14
A17: Gross Profit | B17: =B4-B15 | C17: =C4-C15 | D17: =D4-D15 | E17: =E4-E15 | F17: =F4-F15 | G17: =G4-G15 | H17: =H4-H15
A19: OPERATING EXPENSES
A20: Salaries & Wages | B20: 650000 | C20: 1250000 | D20: 2025000 | E20: 2800000 | F20: 3850000 | G20: 5600000 | H20: 6360000 | I20: ~$30K avg cost/head (KSA rates)
A21: Technology & IT | B21: =B4*0.08 | C21: =C4*0.08 | D21: =D4*0.08 | E21: =E4*0.08 | F21: =F4*0.08 | G21: =G4*0.08 | H21: =H4*0.08
A22: Marketing & BD | B22: =B4*0.1 | C22: =C4*0.1 | D22: =D4*0.08 | E22: =E4*0.07 | F22: =F4*0.06 | G22: =G4*0.05 | H22: =H4*0.04
A23: Rent & Facilities | B23: 200000 | C23: =B23*1.1 | D23: =C23*1.1 | E23: =D23*1.1 | F23: =E23*1.1 | G23: =F23*1.1 | H23: =G23*1.1
A24: G&A | B24: =B4*0.05 | C24: =C4*0.05 | D24: =D4*0.05 | E24: =E4*0.05 | F24: =F4*0.05 | G24: =G4*0.05 | H24: =H4*0.05
A26: Total Operating Expenses | B26: =SUM(B20:B24) | C26: =SUM(C20:C24) | D26: =SUM(D20:D24) | E26: =SUM(E20:E24) | F26: =SUM(F20:F24) | G26: =SUM(G20:G24) | H26: =SUM(H20:H24)
A28: EBITDA
A29: EBITDA | B29: =B17-B26 | C29: =C17-C26 | D29: =D17-D26 | E29: =E17-E26 | F29: =F17-F26 | G29: =G17-G26 | H29: =H17-H26
A30: EBITDA Margin % | B30: =IF(B4=0,0,B29/B4) | C30: =IF(C4=0,0,C29/C4) | D30: =IF(D4=0,0,D29/D4) | E30: =IF(E4=0,0,E29/E4) | F30: =IF(F4=0,0,F29/F4) | G30: =IF(G4=0,0,G29/G4) | H30: =IF(H4=0,0,H29/H4)
A32: KEY METRICS
A33: Headcount | B33: 13 | C33: 25 | D33: 45 | E33: 70 | F33: 110 | G33: 160 | H33: 160
A34: Revenue / Employee | B34: =IF(B33=0,0,B4/B33) | C34: =IF(C33=0,0,C4/C33) | D34: =IF(D33=0,0,D4/D33) | E34: =IF(E33=0,0,E4/E33) | F34: =IF(F33=0,0,F4/F33) | G34: =IF(G33=0,0,G4/G33) | H34: =IF(H33=0,0,H4/H33)
A36: INVESTMENT
A37: Investment Deployed | B37: 2500000 | C37: 2500000 | D37: 0 | E37: 0 | F37: 0 | G37: 0 | H37: 0
A38: Cumulative Investment | B38: =B37 | C38: =B38+C37 | D38: =C38+D37 | E38: =D38+E37 | F38: =E38+F37 | G38: =F38+G37 | H38: =G38+H37
A40: VALUATION
A41: Current Valuation (DCF) | B41: 60000000
A42: Target Valuation (2030) | B42: 100000000

Sheet Waraqa
A1: Waraqa — Detailed P&L
A2: ($, USD) | B2: Year 1 | C2: Year 2 | D2: Year 3 | E2: Year 4 | F2: Year 5 | G2: Notes
A3: REVENUE
A4: Total Revenue | B4: 1200000 | C4: 3500000 | D4: 7500000 | E4: 14000000 | F4: 24000000
A5: Journal Hosting & Mgmt (35%) | B5: =B$4*0.35 | C5: =C$4*0.35 | D5: =D$4*0.35 | E5: =E$4*0.35 | F5: =F$4*0.35
A6: Article Processing Charges (20%) | B6: =B$4*0.2 | C6: =C$4*0.2 | D6: =D$4*0.2 | E6: =E$4*0.2 | F6: =F$4*0.2
A7: Evidence Synthesis Projects (20%) | B7: =B$4*0.2 | C7: =C$4*0.2 | D7: =D$4*0.2 | E7: =E$4*0.2 | F7: =F$4*0.2
A8: Manuscript Services (10%) | B8: =B$4*0.1 | C8: =C$4*0.1 | D8: =D$4*0.1 | E8: =E$4*0.1 | F8: =F$4*0.1
A9: Data Registry Subscriptions (10%) | B9: =B$4*0.1 | C9: =C$4*0.1 | D9: =D$4*0.1 | E9: =E$4*0.1 | F9: =F$4*0.1
A10: Platform Licensing (5%) | B10: =B$4*0.05 | C10: =C$4*0.05 | D10: =D$4*0.05 | E10: =E$4*0.05 | F10: =F$4*0.05
A12: COST OF REVENUE
A13: COGS (33% of Revenue) | B13: =B4*0.33 | C13: =C4*0.33 | D13: =D4*0.33 | E13: =E4*0.33 | F13: =F4*0.33
A15: Gross Profit | B15: =B4-B13 | C15: =C4-C13 | D15: =D4-D13 | E15: =E4-E13 | F15: =F4-F13
A16: Gross Margin % | B16: =IF(B4=0,0,B15/B4) | C16: =IF(C4=0,0,C15/C4) | D16: =IF(D4=0,0,D15/D4) | E16: =IF(E4=0,0,E15/E4) | F16: =IF(F4=0,0,F15/F4)
A18: OPERATING EXPENSES
A19: Technology (20%→10%) | B19: =B4*0.2 | C19: =C4*0.18 | D19: =D4*0.15 | E19: =E4*0.12 | F19: =F4*0.1
A20: Content & Editorial (15%→6%) | B20: =B4*0.15 | C20: =C4*0.13 | D20: =D4*0.1 | E20: =E4*0.08 | F20: =F4*0.06
A21: Sales & Marketing (12%→5%) | B21: =B4*0.12 | C21: =C4*0.1 | D21: =D4*0.08 | E21: =E4*0.06 | F21: =F4*0.05
A22: G&A (8%→3%) | B22: =B4*0.08 | C22: =C4*0.06 | D22: =D4*0.05 | E22: =E4*0.04 | F22: =F4*0.03
A24: Total Operating Expenses | B24: =SUM(B19:B22) | C24: =SUM(C19:C22) | D24: =SUM(D19:D22) | E24: =SUM(E19:E22) | F24: =SUM(F19:F22)
A26: EBITDA
A27: EBITDA | B27: =B15-B24 | C27: =C15-C24 | D27: =D15-D24 | E27: =E15-E24 | F27: =F15-F24
A28: EBITDA Margin % | B28: =IF(B4=0,0,B27/B4) | C28: =IF(C4=0,0,C27/C4) | D28: =IF(D4=0,0,D27/D4) | E28: =IF(E4=0,0,E27/E4) | F28: =IF(F4=0,0,F27/F4)
A30: KEY METRICS
A31: Headcount | B31: 8 | C31: 15 | D31: 22 | E31: 30 | F31: 40
A33: INVESTMENT
A34: MVP Capital (Y1) | B34: 1000000
A35: Scaling Capital (Y2) | B35: 1500000
A36: Total Investment | B36: =B34+B35
A37: TAM | B37: $1,264M
A38: SAM | B38: $18.3M
A39: SOM | B39: $4.6-6.6M

Sheet NAMA Knowledge
A1: NAMA Knowledge — Detailed P&L
A2: ($, USD) | B2: Year 1 | C2: Year 2 | D2: Year 3 | E2: Year 4 | F2: Year 5 | G2: Notes
A3: REVENUE
A4: Total Revenue | B4: 1500000 | C4: 4000000 | D4: 9000000 | E4: 17000000 | F4: 28000000
A5: Institutional LMS Licenses (30%) | B5: =B$4*0.3 | C5: =C$4*0.3 | D5: =D$4*0.3 | E5: =E$4*0.3 | F5: =F$4*0.3
A6: Individual CME Subscriptions (15%) | B6: =B$4*0.15 | C6: =C$4*0.15 | D6: =D$4*0.15 | E6: =E$4*0.15 | F6: =F$4*0.15
A7: Simulation Training (20%) | B7: =B$4*0.2 | C7: =C$4*0.2 | D7: =D$4*0.2 | E7: =E$4*0.2 | F7: =F$4*0.2
A8: Pharma-Sponsored Education (20%) | B8: =B$4*0.2 | C8: =C$4*0.2 | D8: =D$4*0.2 | E8: =E$4*0.2 | F8: =F$4*0.2
A9: Conference Management (10%) | B9: =B$4*0.1 | C9: =C$4*0.1 | D9: =D$4*0.1 | E9: =E$4*0.1 | F9: =F$4*0.1
A10: Certification Fees (5%) | B10: =B$4*0.05 | C10: =C$4*0.05 | D10: =D$4*0.05 | E10: =E$4*0.05 | F10: =F$4*0.05
A12: COST OF REVENUE
A13: COGS (28% of Revenue) | B13: =B4*0.28 | C13: =C4*0.28 | D13: =D4*0.28 | E13: =E4*0.28 | F13: =F4*0.28
A15: Gross Profit | B15: =B4-B13 | C15: =C4-C13 | D15: =D4-D13 | E15: =E4-E13 | F15: =F4-F13
A16: Gross Margin % | B16: =IF(B4=0,0,B15/B4) | C16: =IF(C4=0,0,C15/C4) | D16: =IF(D4=0,0,D15/D4) | E16: =IF(E4=0,0,E15/E4) | F16: =IF(F4=0,0,F15/F4)
A18: OPERATING EXPENSES
A19: Content Development (18%→8%) | B19: =B4*0.18 | C19: =C4*0.15 | D19: =D4*0.12 | E19: =E4*0.1 | F19: =F4*0.08
A20: Technology (15%→7%) | B20: =B4*0.15 | C20: =C4*0.13 | D20: =D4*0.1 | E20: =E4*0.08 | F20: =F4*0.07
A21: Operations (12%→5%) | B21: =B4*0.12 | C21: =C4*0.1 | D21: =D4*0.08 | E21: =E4*0.06 | F21: =F4*0.05
A22: Sales & Marketing (10%→4%) | B22: =B4*0.1 | C22: =C4*0.08 | D22: =D4*0.07 | E22: =E4*0.05 | F22: =F4*0.04
A23: G&A (5%→2%) | B23: =B4*0.05 | C23: =C4*0.04 | D23: =D4*0.03 | E23: =E4*0.03 | F23: =F4*0.02
A25: Total Operating Expenses | B25: =SUM(B19:B23) | C25: =SUM(C19:C23) | D25: =SUM(D19:D23) | E25: =SUM(E19:E23) | F25: =SUM(F19:F23)
A27: EBITDA
A28: EBITDA | B28: =B15-B25 | C28: =C15-C25 | D28: =D15-D25 | E28: =E15-E25 | F28: =F15-F25
A29: EBITDA Margin % | B29: =IF(B4=0,0,B28/B4) | C29: =IF(C4=0,0,C28/C4) | D29: =IF(D4=0,0,D28/D4) | E29: =IF(E4=0,0,E28/E4) | F29: =IF(F4=0,0,F28/F4)
A31: KEY METRICS
A32: Headcount | B32: 10 | C32: 18 | D32: 30 | E32: 45 | F32: 60
A34: INVESTMENT
A35: Seed / Pre-Series A | B35: 1000000
A36: Series B | B36: 0
A37: Total Investment | B37: =B35+B36

Sheet NAMA BIO
A1: NAMA BIO — Detailed P&L
A2: ($, USD) | B2: 2026 | C2: 2027 | D2: 2028 | E2: 2029 | F2: 2030 | G2: 2031 | H2: Notes
A3: REVENUE
A4: Total Revenue | B4: 2733333 | C4: 4466667 | D4: 6866667 | E4: 9733333 | F4: 12933333 | G4: 15746667
A5: BE Studies (60%) | B5: =B$4*0.6 | C5: =C$4*0.6 | D5: =D$4*0.6 | E5: =E$4*0.6 | F5: =F$4*0.6 | G5: =G$4*0.6
A6: Bioanalytical (20%) | B6: =B$4*0.2 | C6: =C$4*0.2 | D6: =D$4*0.2 | E6: =E$4*0.2 | F6: =F$4*0.2 | G6: =G$4*0.2
A7: Regulatory (10%) | B7: =B$4*0.1 | C7: =C$4*0.1 | D7: =D$4*0.1 | E7: =E$4*0.1 | F7: =F$4*0.1 | G7: =G$4*0.1
A8: Training (5%) | B8: =B$4*0.05 | C8: =C$4*0.05 | D8: =D$4*0.05 | E8: =E$4*0.05 | F8: =F$4*0.05 | G8: =G$4*0.05
A9: Stability (5%) | B9: =B$4*0.05 | C9: =C$4*0.05 | D9: =D$4*0.05 | E9: =E$4*0.05 | F9: =F$4*0.05 | G9: =G$4*0.05
A11: COST OF REVENUE
A12: COGS | B12: 1106667 | C12: 1466667 | D12: 2106667 | E12: 2786667 | F12: 3786667 | G12: 5493333
A14: Gross Profit | B14: =B4-B12 | C14: =C4-C12 | D14: =D4-D12 | E14: =E4-E12 | F14: =F4-F12 | G14: =G4-G12
A15: Gross Margin % | B15: =IF(B4=0,0,B14/B4) | C15: =IF(C4=0,0,C14/C4) | D15: =IF(D4=0,0,D14/D4) | E15: =IF(E4=0,0,E14/E4) | F15: =IF(F4=0,0,F14/F4) | G15: =IF(G4=0,0,G14/G4)
A17: OPERATING EXPENSES
A18: Total OpEx | B18: 1186667 | C18: 1506667 | D18: 1866667 | E18: 2480000 | F18: 2880000 | G18: 3993333
A20: NET INCOME
A21: Net Income | B21: 308000 | C21: 1225333 | D21: 2348000 | E21: 3560000 | F21: 5013333 | G21: 5260000
A22: Net Margin % | B22: =IF(B4=0,0,B21/B4) | C22: =IF(C4=0,0,C21/C4) | D22: =IF(D4=0,0,D21/D4) | E22: =IF(E4=0,0,E21/E4) | F22: =IF(F4=0,0,F21/F4) | G22: =IF(G4=0,0,G21/G4)
A24: KEY METRICS
A25: Study Capacity | B25: 20 | C25: 40 | D25: 65 | E25: 85 | F25: 100 | G25: 125
A27: INVESTMENT
A28: Stage I (2026) | B28: 1500000
A29: Stage II (2027-2028) | B29: 3000000
A30: Total Investment | B30: =B28+B29
A32: Valuation Target (2031) | B32: 50000000
A34: Partners | B34: CARE Medical, KFSHRC

Sheet Consolidated P&L
A1: Saudi Clinical Intelligence Group — Consolidated P&L
A2: ($, USD) | B2: 2026 | C2: 2027 | D2: 2028 | E2: 2029 | F2: 2030 | G2: 2031 | H2: Notes
A3: REVENUE BY COMPANY
A4: NAMA Medical | B4: ='NAMA Medical'!C4 | C4: ='NAMA Medical'!D4 | D4: ='NAMA Medical'!E4 | E4: ='NAMA Medical'!F4 | F4: ='NAMA Medical'!G4 | G4: ='NAMA Medical'!H4
A5: Waraqa | B5: =Waraqa!B4 | C5: =Waraqa!C4 | D5: =Waraqa!D4 | E5: =Waraqa!E4 | F5: =Waraqa!F4 | G5: 0
A6: NAMA Knowledge | B6: ='NAMA Knowledge'!B4 | C6: ='NAMA Knowledge'!C4 | D6: ='NAMA Knowledge'!D4 | E6: ='NAMA Knowledge'!E4 | F6: ='NAMA Knowledge'!F4 | G6: 0
A7: NAMA BIO | B7: ='NAMA BIO'!B4 | C7: ='NAMA BIO'!C4 | D7: ='NAMA BIO'!D4 | E7: ='NAMA BIO'!E4 | F7: ='NAMA BIO'!F4 | G7: ='NAMA BIO'!G4
A9: Total Group Revenue | B9: =SUM(B4:B7) | C9: =SUM(C4:C7) | D9: =SUM(D4:D7) | E9: =SUM(E4:E7) | F9: =SUM(F4:F7) | G9: =SUM(G4:G7)
A10: YoY Growth % | B10: N/A | C10: =(C9-B9)/B9 | D10: =(D9-C9)/C9 | E10: =(E9-D9)/D9 | F10: =(F9-E9)/E9 | G10: =(G9-F9)/F9
A12: COST OF REVENUE
A13: NAMA Medical COGS | B13: ='NAMA Medical'!C15 | C13: ='NAMA Medical'!D15 | D13: ='NAMA Medical'!E15 | E13: ='NAMA Medical'!F15 | F13: ='NAMA Medical'!G15 | G13: ='NAMA Medical'!H15
A14: Waraqa COGS | B14: =Waraqa!B13 | C14: =Waraqa!C13 | D14: =Waraqa!D13 | E14: =Waraqa!E13 | F14: =Waraqa!F13 | G14: 0
A15: NAMA Knowledge COGS | B15: ='NAMA Knowledge'!B13 | C15: ='NAMA Knowledge'!C13 | D15: ='NAMA Knowledge'!D13 | E15: ='NAMA Knowledge'!E13 | F15: ='NAMA Knowledge'!F13 | G15: 0
A16: NAMA BIO COGS | B16: ='NAMA BIO'!B12 | C16: ='NAMA BIO'!C12 | D16: ='NAMA BIO'!D12 | E16: ='NAMA BIO'!E12 | F16: ='NAMA BIO'!F12 | G16: ='NAMA BIO'!G12
A17: Total Group COGS | B17: =SUM(B13:B16) | C17: =SUM(C13:C16) | D17: =SUM(D13:D16) | E17: =SUM(E13:E16) | F17: =SUM(F13:F16) | G17: =SUM(G13:G16)
A19: Total Gross Profit | B19: =B9-B17 | C19: =C9-C17 | D19: =D9-D17 | E19: =E9-E17 | F19: =F9-F17 | G19: =G9-G17
A20: Gross Margin % | B20: =IF(B9=0,0,B19/B9) | C20: =IF(C9=0,0,C19/C9) | D20: =IF(D9=0,0,D19/D9) | E20: =IF(E9=0,0,E19/E9) | F20: =IF(F9=0,0,F19/F9) | G20: =IF(G9=0,0,G19/G9)
A22: OPERATING EXPENSES
A23: NAMA Medical OpEx | B23: ='NAMA Medical'!C26 | C23: ='NAMA Medical'!D26 | D23: ='NAMA Medical'!E26 | E23: ='NAMA Medical'!F26 | F23: ='NAMA Medical'!G26 | G23: ='NAMA Medical'!H26
A24: Waraqa OpEx | B24: =Waraqa!B24 | C24: =Waraqa!C24 | D24: =Waraqa!D24 | E24: =Waraqa!E24 | F24: =Waraqa!F24 | G24: 0
A25: NAMA Knowledge OpEx | B25: ='NAMA Knowledge'!B25 | C25: ='NAMA Knowledge'!C25 | D25: ='NAMA Knowledge'!D25 | E25: ='NAMA Knowledge'!E25 | F25: ='NAMA Knowledge'!F25 | G25: 0
A26: NAMA BIO OpEx | B26: ='NAMA BIO'!B18 | C26: ='NAMA BIO'!C18 | D26: ='NAMA BIO'!D18 | E26: ='NAMA BIO'!E18 | F26: ='NAMA BIO'!F18 | G26: ='NAMA BIO'!G18
A27: Total Group OpEx | B27: =SUM(B23:B26) | C27: =SUM(C23:C26) | D27: =SUM(D23:D26) | E27: =SUM(E23:E26) | F27: =SUM(F23:F26) | G27: =SUM(G23:G26)
A29: Total EBITDA | B29: =B19-B27 | C29: =C19-C27 | D29: =D19-D27 | E29: =E19-E27 | F29: =F19-F27 | G29: =G19-G27
A30: EBITDA Margin % | B30: =IF(B9=0,0,B29/B9) | C30: =IF(C9=0,0,C29/C9) | D30: =IF(D9=0,0,D29/D9) | E30: =IF(E9=0,0,E29/E9) | F30: =IF(F9=0,0,F29/F9) | G30: =IF(G9=0,0,G29/G9)
A32: HEADCOUNT
A33: NAMA Medical | B33: ='NAMA Medical'!C33 | C33: ='NAMA Medical'!D33 | D33: ='NAMA Medical'!E33 | E33: ='NAMA Medical'!F33 | F33: ='NAMA Medical'!G33 | G33: ='NAMA Medical'!H33
A34: Waraqa | B34: =Waraqa!B31 | C34: =Waraqa!C31 | D34: =Waraqa!D31 | E34: =Waraqa!E31 | F34: =Waraqa!F31 | G34: 0
A35: NAMA Knowledge | B35: ='NAMA Knowledge'!B32 | C35: ='NAMA Knowledge'!C32 | D35: ='NAMA Knowledge'!D32 | E35: ='NAMA Knowledge'!E32 | F35: ='NAMA Knowledge'!F32 | G35: 0
A36: NAMA BIO (est.) | B36: 15 | C36: 25 | D36: 35 | E36: 45 | F36: 55 | G36: 65
A37: Total Group Headcount | B37: =SUM(B33:B36) | C37: =SUM(C33:C36) | D37: =SUM(D33:D36) | E37: =SUM(E33:E36) | F37: =SUM(F33:F36) | G37: =SUM(G33:G36)
A39: INVESTMENT DEPLOYED
A40: Cumulative Investment | B40: 5500000 | C40: 11500000 | D40: 13000000 | E40: 13000000 | F40: 13000000 | G40: 13000000

Sheet Investment & Returns
A1: Investment & Returns Analysis
A3: CAPITAL REQUIREMENTS | B3: Investment | C3: % of Total | D3: Stage
A4: NAMA Medical | B4: 5000000 | C4: =B4/$B$8 | D4: Growth (Y1-Y2)
A5: Waraqa | B5: 2500000 | C5: =B5/$B$8 | D5: MVP + Scale (Y1-Y2)
A6: NAMA Knowledge | B6: 1000000 | C6: =B6/$B$8 | D6: Seed / MVP (Y1-Y2)
A7: NAMA BIO | B7: 4500000 | C7: =B7/$B$8 | D7: Stage I + II (Y1-Y3)
A8: TOTAL | B8: =SUM(B4:B7) | C8: =SUM(C4:C7)
A10: DEPLOYMENT SCHEDULE | B10: 2026 | C10: 2027 | D10: 2028 | E10: 2029 | F10: 2030 | G10: 2031
A11: NAMA Medical | B11: 2500000 | C11: 2500000 | D11: 0 | E11: 0 | F11: 0 | G11: 0
A12: Waraqa | B12: 1000000 | C12: 1500000 | D12: 0 | E12: 0 | F12: 0 | G12: 0
A13: NAMA Knowledge | B13: 500000 | C13: 500000 | D13: 0 | E13: 0 | F13: 0 | G13: 0
A14: NAMA BIO | B14: 1500000 | C14: 1500000 | D14: 1500000 | E14: 0 | F14: 0 | G14: 0
A15: Annual Deployment | B15: =SUM(B11:B14) | C15: =SUM(C11:C14) | D15: =SUM(D11:D14) | E15: =SUM(E11:E14) | F15: =SUM(F11:F14) | G15: =SUM(G11:G14)
A16: Cumulative | B16: =B15 | C16: =B16+C15 | D16: =C16+D15 | E16: =D16+E15 | F16: =E16+F15 | G16: =F16+G15
A18: REVENUE MULTIPLE ANALYSIS (EV/Revenue) | C18: 3x | D18: 5x | E18: 8x
A19: 2030 Revenue (Peak) | B19: ='Consolidated P&L'!F9 | C19: =B19*3 | D19: =B19*5 | E19: =B19*8
A20: 2031 Revenue | B20: ='Consolidated P&L'!G9 | C20: =B20*3 | D20: =B20*5 | E20: =B20*8
A21: MOIC on $13M Investment | C21: =C19/$B$8 | D21: =D19/$B$8 | E21: =E19/$B$8
A23: EBITDA MULTIPLE ANALYSIS (EV/EBITDA) | C23: 10x | D23: 15x | E23: 20x
A24: 2030 EBITDA | B24: ='Consolidated P&L'!F29 | C24: =B24*10 | D24: =B24*15 | E24: =B24*20
A25: 2031 EBITDA | B25: ='Consolidated P&L'!G29 | C25: =B25*10 | D25: =B25*15 | E25: =B25*20
A26: MOIC on $13M Investment | C26: =C24/$B$8 | D26: =D24/$B$8 | E26: =E24/$B$8
A28: EXIT SCENARIOS | B28: Conservative | C28: Base Case | D28: Optimistic
A29: Exit Valuation (2031) | B29: 200000000 | C29: 354000000 | D29: 500000000
A30: Total Investment | B30: =$B$8 | C30: =$B$8 | D30: =$B$8
A31: MOIC | B31: =B29/B30 | C31: =C29/C30 | D31: =D29/D30
A32: Hold Period (years) | B32: 5 | C32: 5 | D32: 5
A33: IRR | B33: =(B29/B30)^(1/B32)-1 | C33: =(C29/C30)^(1/C32)-1 | D33: =(D29/D30)^(1/D32)-1
A34: Net Return | B34: =B29-B30 | C34: =C29-C30 | D34: =D29-D30

Sheet Assumptions
A1: Key Model Assumptions
A3: GENERAL ASSUMPTIONS | B3: Value | C3: Unit | D3: Notes
A4: Currency | B4: USD | D4: All figures in US Dollars
A5: Tax Rate (Saudi Zakat) | B5: 0.2 | C5: % | D5: Saudi corporate Zakat rate
A6: Discount Rate for DCF | B6: 0.15 | C6: % | D6: WACC / cost of capital
A7: Terminal Growth Rate | B7: 0.03 | C7: % | D7: Long-term perpetuity growth
A8: Model Horizon | B8: 2025-2031 | C8: Years | D8: 6-7 year projection
A9: Total Investment | B9: 22500000 | C9: USD | D9: Across all 4 companies
A10: Exit Year | B10: 2031 | D10: 5-year hold from 2026
A12: REVENUE GROWTH RATES BY COMPANY
A13: NAMA Medical | B13: $300K → $40M | C13: 74.1% CAGR | D13: CRO market penetration + AI upside
A14: Waraqa | B14: $1.2M → $24M | C14: 82.1% CAGR | D14: Platform + APC revenue model
A15: NAMA Knowledge | B15: $1.5M → $28M | C15: 79.6% CAGR | D15: LMS + CME subscription growth
A16: NAMA BIO | B16: $2.7M → $15.7M | C16: 41.9% CAGR | D16: Lab capacity expansion 20→125 studies
A18: MARGIN IMPROVEMENT TRAJECTORIES
A19: NAMA Medical | B19: COGS: 35% → 30% | C19: EBITDA: 52.5% target | D19: Scale-driven margin expansion
A20: Waraqa | B20: COGS: 33% fixed | C20: EBITDA: 45% target | D20: Platform economics; low marginal cost
A21: NAMA Knowledge | B21: COGS: 28% fixed | C21: EBITDA: 34% target | D21: High digital margin; content investment
A22: NAMA BIO | B22: COGS: 40%-35% | C22: EBITDA: 40% target | D22: Lab utilization drives margin
A24: HEADCOUNT GROWTH RATES
A25: NAMA Medical | B25: 13 → 212 | C25: 16.3x growth | D25: CRO staff, PIs, medical writers
A26: Waraqa | B26: 6 → 40 | C26: 6.7x growth | D26: Tech + editorial team
A27: NAMA Knowledge | B27: 25 → 140 | C27: 5.6x growth | D27: Content developers, trainers, ops
A28: NAMA BIO | B28: 15 → 65 (est.) | C28: 4.3x growth | D28: Lab technicians, QA, regulatory
A30: MARKET SIZES (TAM / SAM / SOM)
A31: NAMA Medical | B31: Global CRO: $80B+ | C31: MENA CRO: ~$2B | D31: Saudi focus; GCC expansion
A32: Waraqa | B32: TAM: $1,264M | C32: SAM: $18.3M / SOM: $4.6-6.6M | D32: Academic publishing MENA
A33: NAMA Knowledge | B33: MedEd: $10B+ global | C33: MENA CME: ~$500M | D33: Digitization tailwind in KSA
A34: NAMA BIO | B34: BE Market: $3B+ global | C34: KSA/GCC: ~$200M | D34: SFDA regulatory push

Sheet Capital Audit
A1: CAPITAL ALLOCATION AUDIT & COMMENTARY
A2: Saudi Clinical Intelligence Group — VC Analyst Review | Saudi/GCC-Calibrated
A4: REVISED CAPITAL ALLOCATION | B4: Previous | C4: Revised | D4: Change | E4: MVP Stage | F4: Scaling Stage
A5: NAMA Medical | B5: 5000000 | C5: 5000000 | D5: =C5-B5 | E5: 2000000 | F5: 3000000
A6: Waraqa | B6: 1000000 | C6: 2500000 | D6: =C6-B6 | E6: 1000000 | F6: 1500000
A7: NAMA Knowledge | B7: 12000000 | C7: 1000000 | D7: =C7-B7 | E7: 500000 | F7: 500000
A8: NAMA BIO | B8: 4500000 | C8: 4500000 | D8: =C8-B8 | E8: 2000000 | F8: 2500000
A9: TOTAL | B9: =SUM(B5:B8) | C9: =SUM(C5:C8) | D9: =C9-B9 | E9: =SUM(E5:E8) | F9: =SUM(F5:F8)
A11: CAPITAL EFFICIENCY ANALYSIS | B11: Capital / Y1 Rev | C11: Rev / $ Invested (Y5) | D11: Capital / Employee (Y1) | E11: Revenue / Emp (Y5) | F11: Rating
A12: NAMA Medical | B12: =C5/2500000 | C12: =40000000/C5 | D12: =C5/25 | E12: =40000000/160 | F12: ✅ Reasonable
A13: Waraqa | B13: =C6/1200000 | C13: =24000000/C6 | D13: =C6/8 | E13: =24000000/40 | F13: ✅ Now adequate
A14: NAMA Knowledge | B14: =C7/1500000 | C14: =28000000/C7 | D14: =C7/10 | E14: =28000000/60 | F14: ✅ Right-sized
A15: NAMA BIO | B15: =C8/2733333 | C15: =15746667/C8 | D15: =C8/15 | E15: =15746667/65 | F15: ✅ Lab-appropriate
A17: AUDIT FINDINGS & MODELING ERRORS IDENTIFIED
A18: # | B18: Finding
A19: 1 | B19: NAMA Knowledge $12M allocation was 12x revenue — no LMS/CME platform requires this. Reduced to $1M (MVP + Scale).
A20: 2 | B20: Waraqa at $1M was underfunded — cannot cover AI/ML compute + engineering payroll. Raised to $2.5M.
A21: 3 | B21: NAMA Knowledge headcount of 25 at Y1 for $1.5M rev = $60K/head. Reduced to 10 (KSA benchmark: $150K/head).
A22: 4 | B22: NAMA Knowledge Y5 headcount 140 for $28M rev = $200K/head. Reduced to 60 ($467K/head, healthy SaaS metric).
A23: 5 | B23: Waraqa Y5 revenue ($24M) exceeds its own SAM ($18.3M). Structurally impossible without intl expansion not modeled.
A24: 6 | B24: NAMA Medical Y7 headcount 212 reduced to 160. AI-augmented CRO should achieve $250K rev/head at scale.
A25: 7 | B25: Original model OpEx % sums exceeded 100% for Waraqa (103%) and NK (100%). Previous fix applied scale reductions.
A26: 8 | B26: Total capital reduced $22.5M → $13M (42% reduction). Capital efficiency: MOIC improves from 15.7x to 27.2x on base.
A27: 9 | B27: NAMA BIO is the best-calibrated entity — actual financial data, realistic 42% CAGR, lab-appropriate capex.
A28: 10 | B28: Deployment now front-loaded: 42% Y1, 46% Y2, 12% Y3. Full deployment by 2028 vs. previous 2028 completion.
A30: SENSITIVITY ANALYSIS — EXIT VALUATION vs. INVESTMENT (MOIC)
A31: Exit Valuation → | B31: $150M | C31: $200M | D31: $354M | E31: $500M | F31: $750M
A32: MOIC ($13M invested) | B32: =150000000/$C$9 | C32: =200000000/$C$9 | D32: =354000000/$C$9 | E32: =500000000/$C$9 | F32: =750000000/$C$9
A33: IRR (5yr hold) | B33: =(150000000/$C$9)^(1/5)-1 | C33: =(200000000/$C$9)^(1/5)-1 | D33: =(354000000/$C$9)^(1/5)-1 | E33: =(500000000/$C$9)^(1/5)-1 | F33: =(750000000/$C$9)^(1/5)-1
A34: Net Return | B34: =150000000-$C$9 | C34: =200000000-$C$9 | D34: =354000000-$C$9 | E34: =500000000-$C$9 | F34: =750000000-$C$9
A35: MOIC ($22.5M — OLD) | B35: =150000000/$B$9 | C35: =200000000/$B$9 | D35: =354000000/$B$9 | E35: =500000000/$B$9 | F35: =750000000/$B$9
A37: REVENUE GROWTH FLAG SUMMARY
A38: Company | B38: 5yr CAGR | C38: Y5 Revenue | D38: SAM Check | E38: Flag | F38: Commentary
A39: NAMA Medical | B39: 0.741 | C39: 40000000 | D39: Within MENA CRO TAM | E39: ⚠️ Aggressive | F39: Plausible if Vision 2030 pharma demand materializes
A40: Waraqa | B40: 0.821 | C40: 24000000 | D40: EXCEEDS SAM ($18.3M) | E40: 🔴 Unrealistic | F40: Y5 revenue exceeds addressable market. Needs intl expansion to justify.
A41: NAMA Knowledge | B41: 0.796 | C41: 28000000 | D41: Requires GCC-wide scale | E41: ⚠️ Aggressive | F41: Achievable with pharma sponsorships but aggressive for KSA-only
A42: NAMA BIO | B42: 0.419 | C42: 15746667 | D42: Well within KSA/GCC BE market | E42: ✅ Realistic | F42: Based on actual financials. Lab capacity ramp is credible.
